<?xml version="1.0"?>
<groundnet>
  <version>Sat, 04 Jul 2020 18:10:16 GMT by FlightgearAirports</version>
  <name>gooneybird</name>
  <frequencies>
    <APPROACH>12107</APPROACH>
    <GROUND>13145</GROUND>
    <TOWER>12925</TOWER>
  </frequencies>
  <parkingList>
    <Parking index="0" type="gate" name="EPKT-" lat="N50 28.297" lon="E19 4.15" heading="180.0" radius="40" number="28" pushBackRoute="184"/>
    <Parking index="1" type="gate" name="EPKT-" lat="N50 28.292" lon="E19 4.836" heading="180.0" radius="26" number="11" pushBackRoute="163"/>
    <Parking index="2" type="gate" name="EPKT-" lat="N50 28.307" lon="E19 4.527" heading="232.9" radius="18" number="17" pushBackRoute="170"/>
    <Parking index="3" type="gate" name="EPKT-" lat="N50 28.308" lon="E19 4.44" heading="231.0" radius="14" number="19" pushBackRoute="173"/>
    <Parking index="4" type="gate" name="EPKT-" lat="N50 28.29" lon="E19 4.655" heading="180.0" radius="18" number="14" pushBackRoute="167"/>
    <Parking index="5" type="gate" name="EPKT-" lat="N50 28.291" lon="E19 4.617" heading="180.0" radius="18" number="15" pushBackRoute="168"/>
    <Parking index="6" type="gate" name="EPKT-" lat="N50 28.293" lon="E19 4.779" heading="180.0" radius="26" number="12" pushBackRoute="165"/>
    <Parking index="7" type="gate" name="EPKT-" lat="N50 28.307" lon="E19 4.482" heading="231.0" radius="18" number="18" pushBackRoute="171"/>
    <Parking index="8" type="gate" name="EPKT-" lat="N50 28.305" lon="E19 4.57" heading="234.3" radius="18" number="16" pushBackRoute="169"/>
    <Parking index="9" type="gate" name="EPKT-" lat="N50 28.293" lon="E19 4.723" heading="180.1" radius="26" number="13" pushBackRoute="166"/>
    <Parking index="10" type="gate" name="EPKT-" lat="N50 28.304" lon="E19 4.289" heading="180.0" radius="18" number="23" pushBackRoute="181"/>
    <Parking index="11" type="gate" name="EPKT-" lat="N50 28.289" lon="E19 4.909" heading="180.0" radius="18" number="10" pushBackRoute="161"/>
    <Parking index="12" type="gate" name="EPKT-" lat="N50 28.307" lon="E19 4.405" heading="208.2" radius="18" number="20" pushBackRoute="175"/>
    <Parking index="13" type="gate" name="EPKT-" lat="N50 28.304" lon="E19 4.326" heading="180.0" radius="18" number="22" pushBackRoute="179"/>
    <Parking index="14" type="gate" name="EPKT-" lat="N50 28.297" lon="E19 4.228" heading="180.0" radius="40" number="25" pushBackRoute="182"/>
    <Parking index="15" type="gate" name="EPKT-" lat="N50 28.289" lon="E19 4.948" heading="180.0" radius="18" number="9" pushBackRoute="159"/>
    <Parking index="16" type="gate" name="EPKT-" lat="N50 28.289" lon="E19 5.045" heading="180.0" radius="18" number="7" pushBackRoute="155"/>
    <Parking index="17" type="gate" name="EPKT-" lat="N50 28.289" lon="E19 5.007" heading="180.0" radius="18" number="8" pushBackRoute="157"/>
    <Parking index="18" type="gate" name="EPKT-" lat="N50 28.304" lon="E19 4.367" heading="180.0" radius="18" number="21" pushBackRoute="177"/>
    <Parking index="19" type="gate" name="EPKT-" lat="N50 28.286" lon="E19 5.215" heading="180.2" radius="26" number="1" pushBackRoute="151"/>
    <Parking index="20" type="gate" name="EPKT-" lat="N50 28.288" lon="E19 5.139" heading="180.0" radius="26" number="4" pushBackRoute="152"/>
    <Parking index="21" type="gate" name="EPKT-" lat="N50 28.288" lon="E19 5.083" heading="180.0" radius="18" number="6" pushBackRoute="153"/>
    <Parking index="22" type="cargo" name="undefined" lat="N50 28.278" lon="E19 5.964" heading="179.4" radius="40" number="81" pushBackRoute="129"/>
    <Parking index="23" type="cargo" name="undefined" lat="N50 28.278" lon="E19 5.888" heading="180.0" radius="40" number="84" pushBackRoute="131"/>
    <Parking index="24" type="cargo" name="undefined" lat="N50 28.276" lon="E19 5.81" heading="180.0" radius="33" number="87" pushBackRoute="133"/>
    <Parking index="25" type="cargo" name="undefined" lat="N50 28.275" lon="E19 5.7" heading="180.0" radius="18" number="91" pushBackRoute="139"/>
    <Parking index="26" type="cargo" name="undefined" lat="N50 28.275" lon="E19 5.741" heading="180.0" radius="18" number="89" pushBackRoute="138"/>
    <Parking index="27" type="cargo" name="undefined" lat="N50 28.275" lon="E19 5.652" heading="180.0" radius="18" number="93" pushBackRoute="140"/>
    <Parking index="28" type="cargo" name="undefined" lat="N50 28.275" lon="E19 5.616" heading="180.0" radius="18" number="94" pushBackRoute="141"/>
  </parkingList>
  <TaxiNodes>
    <node index="29" lat="N50 28.558" lon="E19 5.971" isOnRunway="1" holdPointType="none"/>
    <node index="30" lat="N50 28.557" lon="E19 6.189" isOnRunway="0" holdPointType="none"/>
    <node index="31" lat="N50 28.524" lon="E19 6.27" isOnRunway="0" holdPointType="none"/>
    <node index="32" lat="N50 28.483" lon="E19 6.269" isOnRunway="0" holdPointType="none"/>
    <node index="33" lat="N50 28.427" lon="E19 6.185" isOnRunway="0" holdPointType="normal"/>
    <node index="34" lat="N50 28.338" lon="E19 5.996" isOnRunway="0" holdPointType="none"/>
    <node index="35" lat="N50 28.338" lon="E19 5.81" isOnRunway="0" holdPointType="none"/>
    <node index="36" lat="N50 28.339" lon="E19 5.633" isOnRunway="0" holdPointType="none"/>
    <node index="37" lat="N50 28.34" lon="E19 5.151" isOnRunway="0" holdPointType="none"/>
    <node index="38" lat="N50 28.342" lon="E19 4.453" isOnRunway="0" holdPointType="none"/>
    <node index="39" lat="N50 28.342" lon="E19 4.015" isOnRunway="0" holdPointType="none"/>
    <node index="40" lat="N50 28.35" lon="E19 3.987" isOnRunway="0" holdPointType="none"/>
    <node index="41" lat="N50 28.367" lon="E19 3.975" isOnRunway="0" holdPointType="none"/>
    <node index="42" lat="N50 28.423" lon="E19 3.975" isOnRunway="0" holdPointType="normal"/>
    <node index="43" lat="N50 28.457" lon="E19 3.976" isOnRunway="0" holdPointType="none"/>
    <node index="44" lat="N50 28.458" lon="E19 3.638" isOnRunway="0" holdPointType="none"/>
    <node index="45" lat="N50 28.469" lon="E19 3.602" isOnRunway="0" holdPointType="none"/>
    <node index="46" lat="N50 28.486" lon="E19 3.587" isOnRunway="0" holdPointType="none"/>
    <node index="47" lat="N50 28.511" lon="E19 3.589" isOnRunway="0" holdPointType="normal"/>
    <node index="48" lat="N50 28.545" lon="E19 3.594" isOnRunway="0" holdPointType="none"/>
    <node index="49" lat="N50 28.563" lon="E19 3.627" isOnRunway="1" holdPointType="none"/>
    <node index="50" lat="N50 28.454" lon="E19 5.634" isOnRunway="0" holdPointType="none"/>
    <node index="51" lat="N50 28.455" lon="E19 5.152" isOnRunway="0" holdPointType="none"/>
    <node index="52" lat="N50 28.342" lon="E19 4.228" isOnRunway="0" holdPointType="none"/>
    <node index="53" lat="N50 28.342" lon="E19 4.367" isOnRunway="0" holdPointType="none"/>
    <node index="54" lat="N50 28.342" lon="E19 4.15" isOnRunway="0" holdPointType="none"/>
    <node index="55" lat="N50 28.342" lon="E19 4.289" isOnRunway="0" holdPointType="none"/>
    <node index="56" lat="N50 28.342" lon="E19 4.325" isOnRunway="0" holdPointType="none"/>
    <node index="57" lat="N50 28.342" lon="E19 4.416" isOnRunway="0" holdPointType="none"/>
    <node index="58" lat="N50 28.322" lon="E19 4.416" isOnRunway="0" holdPointType="none"/>
    <node index="59" lat="N50 28.314" lon="E19 4.453" isOnRunway="0" holdPointType="none"/>
    <node index="60" lat="N50 28.341" lon="E19 4.802" isOnRunway="0" holdPointType="none"/>
    <node index="61" lat="N50 28.34" lon="E19 5.007" isOnRunway="0" holdPointType="none"/>
    <node index="62" lat="N50 28.341" lon="E19 4.617" isOnRunway="0" holdPointType="none"/>
    <node index="63" lat="N50 28.34" lon="E19 5.083" isOnRunway="0" holdPointType="none"/>
    <node index="64" lat="N50 28.341" lon="E19 4.723" isOnRunway="0" holdPointType="none"/>
    <node index="65" lat="N50 28.34" lon="E19 4.909" isOnRunway="0" holdPointType="none"/>
    <node index="66" lat="N50 28.342" lon="E19 4.543" isOnRunway="0" holdPointType="none"/>
    <node index="67" lat="N50 28.34" lon="E19 5.139" isOnRunway="0" holdPointType="none"/>
    <node index="68" lat="N50 28.341" lon="E19 4.78" isOnRunway="0" holdPointType="none"/>
    <node index="69" lat="N50 28.34" lon="E19 4.948" isOnRunway="0" holdPointType="none"/>
    <node index="70" lat="N50 28.341" lon="E19 4.591" isOnRunway="0" holdPointType="none"/>
    <node index="71" lat="N50 28.34" lon="E19 5.045" isOnRunway="0" holdPointType="none"/>
    <node index="72" lat="N50 28.341" lon="E19 4.655" isOnRunway="0" holdPointType="none"/>
    <node index="73" lat="N50 28.341" lon="E19 4.835" isOnRunway="0" holdPointType="none"/>
    <node index="74" lat="N50 28.342" lon="E19 4.498" isOnRunway="0" holdPointType="none"/>
    <node index="75" lat="N50 28.315" lon="E19 4.499" isOnRunway="0" holdPointType="none"/>
    <node index="76" lat="N50 28.314" lon="E19 4.543" isOnRunway="0" holdPointType="none"/>
    <node index="77" lat="N50 28.315" lon="E19 4.591" isOnRunway="0" holdPointType="none"/>
    <node index="78" lat="N50 28.34" lon="E19 5.216" isOnRunway="0" holdPointType="none"/>
    <node index="79" lat="N50 28.556" lon="E19 3.61" isOnRunway="0" holdPointType="none"/>
    <node index="80" lat="N50 28.535" lon="E19 3.589" isOnRunway="0" holdPointType="none"/>
    <node index="81" lat="N50 28.477" lon="E19 3.592" isOnRunway="0" holdPointType="none"/>
    <node index="82" lat="N50 28.461" lon="E19 3.616" isOnRunway="0" holdPointType="none"/>
    <node index="83" lat="N50 28.459" lon="E19 3.627" isOnRunway="0" holdPointType="none"/>
    <node index="84" lat="N50 28.465" lon="E19 3.608" isOnRunway="0" holdPointType="none"/>
    <node index="85" lat="N50 28.472" lon="E19 3.596" isOnRunway="0" holdPointType="none"/>
    <node index="86" lat="N50 28.481" lon="E19 3.589" isOnRunway="0" holdPointType="none"/>
    <node index="87" lat="N50 28.457" lon="E19 4.006" isOnRunway="0" holdPointType="none"/>
    <node index="88" lat="N50 28.464" lon="E19 4.032" isOnRunway="0" holdPointType="none"/>
    <node index="89" lat="N50 28.497" lon="E19 4.123" isOnRunway="0" holdPointType="none"/>
    <node index="90" lat="N50 28.529" lon="E19 4.21" isOnRunway="0" holdPointType="none"/>
    <node index="91" lat="N50 28.552" lon="E19 4.305" isOnRunway="0" holdPointType="none"/>
    <node index="92" lat="N50 28.561" lon="E19 4.365" isOnRunway="1" holdPointType="none"/>
    <node index="93" lat="N50 28.535" lon="E19 4.215" isOnRunway="0" holdPointType="none"/>
    <node index="94" lat="N50 28.542" lon="E19 4.218" isOnRunway="0" holdPointType="none"/>
    <node index="95" lat="N50 28.548" lon="E19 4.217" isOnRunway="0" holdPointType="none"/>
    <node index="96" lat="N50 28.555" lon="E19 4.212" isOnRunway="0" holdPointType="none"/>
    <node index="97" lat="N50 28.562" lon="E19 4.186" isOnRunway="1" holdPointType="none"/>
    <node index="98" lat="N50 28.457" lon="E19 4.147" isOnRunway="0" holdPointType="none"/>
    <node index="99" lat="N50 28.46" lon="E19 4.133" isOnRunway="0" holdPointType="none"/>
    <node index="100" lat="N50 28.467" lon="E19 4.122" isOnRunway="0" holdPointType="none"/>
    <node index="101" lat="N50 28.472" lon="E19 4.116" isOnRunway="0" holdPointType="none"/>
    <node index="102" lat="N50 28.479" lon="E19 4.114" isOnRunway="0" holdPointType="none"/>
    <node index="103" lat="N50 28.487" lon="E19 4.117" isOnRunway="0" holdPointType="none"/>
    <node index="104" lat="N50 28.488" lon="E19 5.635" isOnRunway="0" holdPointType="none"/>
    <node index="105" lat="N50 28.532" lon="E19 5.635" isOnRunway="0" holdPointType="none"/>
    <node index="106" lat="N50 28.539" lon="E19 5.631" isOnRunway="0" holdPointType="none"/>
    <node index="107" lat="N50 28.545" lon="E19 5.627" isOnRunway="0" holdPointType="none"/>
    <node index="108" lat="N50 28.55" lon="E19 5.621" isOnRunway="0" holdPointType="none"/>
    <node index="109" lat="N50 28.558" lon="E19 5.601" isOnRunway="1" holdPointType="none"/>
    <node index="110" lat="N50 28.348" lon="E19 6.028" isOnRunway="0" holdPointType="none"/>
    <node index="111" lat="N50 28.34" lon="E19 6.012" isOnRunway="0" holdPointType="none"/>
    <node index="112" lat="N50 28.338" lon="E19 6.004" isOnRunway="0" holdPointType="none"/>
    <node index="113" lat="N50 28.459" lon="E19 6.249" isOnRunway="0" holdPointType="none"/>
    <node index="114" lat="N50 28.47" lon="E19 6.264" isOnRunway="0" holdPointType="none"/>
    <node index="115" lat="N50 28.476" lon="E19 6.267" isOnRunway="0" holdPointType="none"/>
    <node index="116" lat="N50 28.464" lon="E19 6.257" isOnRunway="0" holdPointType="none"/>
    <node index="117" lat="N50 28.544" lon="E19 6.26" isOnRunway="0" holdPointType="none"/>
    <node index="118" lat="N50 28.535" lon="E19 6.268" isOnRunway="0" holdPointType="none"/>
    <node index="119" lat="N50 28.557" lon="E19 6.232" isOnRunway="0" holdPointType="none"/>
    <node index="120" lat="N50 28.552" lon="E19 6.246" isOnRunway="0" holdPointType="none"/>
    <node index="121" lat="N50 28.327" lon="E19 4.723" isOnRunway="0" holdPointType="none"/>
    <node index="122" lat="N50 28.338" lon="E19 5.964" isOnRunway="0" holdPointType="none"/>
    <node index="123" lat="N50 28.338" lon="E19 5.887" isOnRunway="0" holdPointType="none"/>
    <node index="124" lat="N50 28.338" lon="E19 5.742" isOnRunway="0" holdPointType="none"/>
    <node index="125" lat="N50 28.338" lon="E19 5.7" isOnRunway="0" holdPointType="none"/>
    <node index="126" lat="N50 28.339" lon="E19 5.651" isOnRunway="0" holdPointType="none"/>
    <node index="127" lat="N50 28.339" lon="E19 5.614" isOnRunway="0" holdPointType="none"/>
    <node index="128" lat="N50 28.317" lon="E19 5.964" isOnRunway="0" holdPointType="none"/>
    <node index="129" lat="N50 28.314" lon="E19 6.002" isOnRunway="0" holdPointType="PushBack"/>
    <node index="130" lat="N50 28.319" lon="E19 5.888" isOnRunway="0" holdPointType="none"/>
    <node index="131" lat="N50 28.318" lon="E19 5.94" isOnRunway="0" holdPointType="PushBack"/>
    <node index="132" lat="N50 28.321" lon="E19 5.81" isOnRunway="0" holdPointType="none"/>
    <node index="133" lat="N50 28.318" lon="E19 5.866" isOnRunway="0" holdPointType="PushBack"/>
    <node index="134" lat="N50 28.314" lon="E19 5.742" isOnRunway="0" holdPointType="none"/>
    <node index="135" lat="N50 28.315" lon="E19 5.7" isOnRunway="0" holdPointType="none"/>
    <node index="136" lat="N50 28.314" lon="E19 5.651" isOnRunway="0" holdPointType="none"/>
    <node index="137" lat="N50 28.312" lon="E19 5.615" isOnRunway="0" holdPointType="none"/>
    <node index="138" lat="N50 28.313" lon="E19 5.787" isOnRunway="0" holdPointType="PushBack"/>
    <node index="139" lat="N50 28.313" lon="E19 5.73" isOnRunway="0" holdPointType="PushBack"/>
    <node index="140" lat="N50 28.311" lon="E19 5.685" isOnRunway="0" holdPointType="PushBack"/>
    <node index="141" lat="N50 28.311" lon="E19 5.64" isOnRunway="0" holdPointType="PushBack"/>
    <node index="142" lat="N50 28.322" lon="E19 5.083" isOnRunway="0" holdPointType="none"/>
    <node index="143" lat="N50 28.32" lon="E19 5.139" isOnRunway="0" holdPointType="none"/>
    <node index="144" lat="N50 28.321" lon="E19 5.216" isOnRunway="0" holdPointType="none"/>
    <node index="145" lat="N50 28.326" lon="E19 4.591" isOnRunway="0" holdPointType="none"/>
    <node index="146" lat="N50 28.33" lon="E19 4.543" isOnRunway="0" holdPointType="none"/>
    <node index="147" lat="N50 28.331" lon="E19 4.498" isOnRunway="0" holdPointType="none"/>
    <node index="148" lat="N50 28.323" lon="E19 4.617" isOnRunway="0" holdPointType="none"/>
    <node index="149" lat="N50 28.326" lon="E19 4.655" isOnRunway="0" holdPointType="none"/>
    <node index="150" lat="N50 28.329" lon="E19 4.228" isOnRunway="0" holdPointType="none"/>
    <node index="151" lat="N50 28.32" lon="E19 5.249" isOnRunway="0" holdPointType="PushBack"/>
    <node index="152" lat="N50 28.319" lon="E19 5.173" isOnRunway="0" holdPointType="PushBack"/>
    <node index="153" lat="N50 28.321" lon="E19 5.118" isOnRunway="0" holdPointType="PushBack"/>
    <node index="154" lat="N50 28.32" lon="E19 5.045" isOnRunway="0" holdPointType="none"/>
    <node index="155" lat="N50 28.319" lon="E19 5.07" isOnRunway="0" holdPointType="PushBack"/>
    <node index="156" lat="N50 28.318" lon="E19 5.007" isOnRunway="0" holdPointType="none"/>
    <node index="157" lat="N50 28.317" lon="E19 5.034" isOnRunway="0" holdPointType="PushBack"/>
    <node index="158" lat="N50 28.319" lon="E19 4.948" isOnRunway="0" holdPointType="none"/>
    <node index="159" lat="N50 28.318" lon="E19 4.985" isOnRunway="0" holdPointType="PushBack"/>
    <node index="160" lat="N50 28.32" lon="E19 4.909" isOnRunway="0" holdPointType="none"/>
    <node index="161" lat="N50 28.319" lon="E19 4.939" isOnRunway="0" holdPointType="PushBack"/>
    <node index="162" lat="N50 28.326" lon="E19 4.836" isOnRunway="0" holdPointType="none"/>
    <node index="163" lat="N50 28.324" lon="E19 4.884" isOnRunway="0" holdPointType="PushBack"/>
    <node index="164" lat="N50 28.325" lon="E19 4.78" isOnRunway="0" holdPointType="none"/>
    <node index="165" lat="N50 28.323" lon="E19 4.823" isOnRunway="0" holdPointType="PushBack"/>
    <node index="166" lat="N50 28.325" lon="E19 4.764" isOnRunway="0" holdPointType="PushBack"/>
    <node index="167" lat="N50 28.324" lon="E19 4.707" isOnRunway="0" holdPointType="PushBack"/>
    <node index="168" lat="N50 28.322" lon="E19 4.645" isOnRunway="0" holdPointType="PushBack"/>
    <node index="169" lat="N50 28.326" lon="E19 4.609" isOnRunway="0" holdPointType="PushBack"/>
    <node index="170" lat="N50 28.33" lon="E19 4.579" isOnRunway="0" holdPointType="PushBack"/>
    <node index="171" lat="N50 28.331" lon="E19 4.527" isOnRunway="0" holdPointType="PushBack"/>
    <node index="172" lat="N50 28.332" lon="E19 4.453" isOnRunway="0" holdPointType="none"/>
    <node index="173" lat="N50 28.331" lon="E19 4.488" isOnRunway="0" holdPointType="PushBack"/>
    <node index="174" lat="N50 28.331" lon="E19 4.416" isOnRunway="0" holdPointType="none"/>
    <node index="175" lat="N50 28.331" lon="E19 4.44" isOnRunway="0" holdPointType="PushBack"/>
    <node index="176" lat="N50 28.331" lon="E19 4.367" isOnRunway="0" holdPointType="none"/>
    <node index="177" lat="N50 28.331" lon="E19 4.4" isOnRunway="0" holdPointType="PushBack"/>
    <node index="178" lat="N50 28.331" lon="E19 4.325" isOnRunway="0" holdPointType="none"/>
    <node index="179" lat="N50 28.33" lon="E19 4.354" isOnRunway="0" holdPointType="PushBack"/>
    <node index="180" lat="N50 28.331" lon="E19 4.289" isOnRunway="0" holdPointType="none"/>
    <node index="181" lat="N50 28.33" lon="E19 4.311" isOnRunway="0" holdPointType="PushBack"/>
    <node index="182" lat="N50 28.327" lon="E19 4.273" isOnRunway="0" holdPointType="PushBack"/>
    <node index="183" lat="N50 28.329" lon="E19 4.15" isOnRunway="0" holdPointType="none"/>
    <node index="184" lat="N50 28.327" lon="E19 4.197" isOnRunway="0" holdPointType="PushBack"/>
    <node index="185" lat="N50 28.314" lon="E19 6.002" isOnRunway="0"/>
    <node index="186" lat="N50 28.318" lon="E19 5.94" isOnRunway="0"/>
    <node index="187" lat="N50 28.318" lon="E19 5.866" isOnRunway="0"/>
    <node index="188" lat="N50 28.313" lon="E19 5.787" isOnRunway="0"/>
    <node index="189" lat="N50 28.313" lon="E19 5.73" isOnRunway="0"/>
    <node index="190" lat="N50 28.311" lon="E19 5.685" isOnRunway="0"/>
    <node index="191" lat="N50 28.311" lon="E19 5.64" isOnRunway="0"/>
    <node index="192" lat="N50 28.32" lon="E19 5.249" isOnRunway="0"/>
    <node index="193" lat="N50 28.319" lon="E19 5.173" isOnRunway="0"/>
    <node index="194" lat="N50 28.321" lon="E19 5.118" isOnRunway="0"/>
    <node index="195" lat="N50 28.319" lon="E19 5.07" isOnRunway="0"/>
    <node index="196" lat="N50 28.317" lon="E19 5.034" isOnRunway="0"/>
    <node index="197" lat="N50 28.318" lon="E19 4.985" isOnRunway="0"/>
    <node index="198" lat="N50 28.319" lon="E19 4.939" isOnRunway="0"/>
    <node index="199" lat="N50 28.324" lon="E19 4.884" isOnRunway="0"/>
    <node index="200" lat="N50 28.323" lon="E19 4.823" isOnRunway="0"/>
    <node index="201" lat="N50 28.325" lon="E19 4.764" isOnRunway="0"/>
    <node index="202" lat="N50 28.324" lon="E19 4.707" isOnRunway="0"/>
    <node index="203" lat="N50 28.322" lon="E19 4.645" isOnRunway="0"/>
    <node index="204" lat="N50 28.326" lon="E19 4.609" isOnRunway="0"/>
    <node index="205" lat="N50 28.33" lon="E19 4.579" isOnRunway="0"/>
    <node index="206" lat="N50 28.331" lon="E19 4.527" isOnRunway="0"/>
    <node index="207" lat="N50 28.331" lon="E19 4.488" isOnRunway="0"/>
    <node index="208" lat="N50 28.331" lon="E19 4.44" isOnRunway="0"/>
    <node index="209" lat="N50 28.331" lon="E19 4.4" isOnRunway="0"/>
    <node index="210" lat="N50 28.33" lon="E19 4.354" isOnRunway="0"/>
    <node index="211" lat="N50 28.33" lon="E19 4.311" isOnRunway="0"/>
    <node index="212" lat="N50 28.327" lon="E19 4.273" isOnRunway="0"/>
    <node index="213" lat="N50 28.327" lon="E19 4.197" isOnRunway="0"/>
  </TaxiNodes>
  <TaxiWaySegments>
    <arc begin="0" end="183" isPushBackRoute="1" name="0"/>
    <arc begin="183" end="0" isPushBackRoute="1" name="0"/>
    <arc begin="1" end="162" isPushBackRoute="1" name="0"/>
    <arc begin="162" end="1" isPushBackRoute="1" name="0"/>
    <arc begin="2" end="76" isPushBackRoute="1" name="0"/>
    <arc begin="76" end="2" isPushBackRoute="1" name="0"/>
    <arc begin="3" end="59" isPushBackRoute="1" name="0"/>
    <arc begin="59" end="3" isPushBackRoute="1" name="0"/>
    <arc begin="4" end="149" isPushBackRoute="1" name="0"/>
    <arc begin="149" end="4" isPushBackRoute="1" name="0"/>
    <arc begin="5" end="148" isPushBackRoute="1" name="0"/>
    <arc begin="148" end="5" isPushBackRoute="1" name="0"/>
    <arc begin="6" end="164" isPushBackRoute="1" name="0"/>
    <arc begin="164" end="6" isPushBackRoute="1" name="0"/>
    <arc begin="7" end="75" isPushBackRoute="1" name="0"/>
    <arc begin="75" end="7" isPushBackRoute="1" name="0"/>
    <arc begin="8" end="77" isPushBackRoute="1" name="0"/>
    <arc begin="77" end="8" isPushBackRoute="1" name="0"/>
    <arc begin="9" end="121" isPushBackRoute="1" name="0"/>
    <arc begin="121" end="9" isPushBackRoute="1" name="0"/>
    <arc begin="10" end="180" isPushBackRoute="1" name="0"/>
    <arc begin="180" end="10" isPushBackRoute="1" name="0"/>
    <arc begin="11" end="160" isPushBackRoute="1" name="0"/>
    <arc begin="160" end="11" isPushBackRoute="1" name="0"/>
    <arc begin="12" end="58" isPushBackRoute="1" name="0"/>
    <arc begin="58" end="12" isPushBackRoute="1" name="0"/>
    <arc begin="13" end="178" isPushBackRoute="1" name="0"/>
    <arc begin="178" end="13" isPushBackRoute="1" name="0"/>
    <arc begin="14" end="150" isPushBackRoute="1" name="0"/>
    <arc begin="150" end="14" isPushBackRoute="1" name="0"/>
    <arc begin="15" end="158" isPushBackRoute="1" name="0"/>
    <arc begin="158" end="15" isPushBackRoute="1" name="0"/>
    <arc begin="16" end="154" isPushBackRoute="1" name="0"/>
    <arc begin="154" end="16" isPushBackRoute="1" name="0"/>
    <arc begin="17" end="156" isPushBackRoute="1" name="0"/>
    <arc begin="156" end="17" isPushBackRoute="1" name="0"/>
    <arc begin="18" end="176" isPushBackRoute="1" name="0"/>
    <arc begin="176" end="18" isPushBackRoute="1" name="0"/>
    <arc begin="19" end="144" isPushBackRoute="1" name="0"/>
    <arc begin="144" end="19" isPushBackRoute="1" name="0"/>
    <arc begin="20" end="143" isPushBackRoute="1" name="0"/>
    <arc begin="143" end="20" isPushBackRoute="1" name="0"/>
    <arc begin="21" end="142" isPushBackRoute="1" name="0"/>
    <arc begin="142" end="21" isPushBackRoute="1" name="0"/>
    <arc begin="29" end="30" isPushBackRoute="0" name="0"/>
    <arc begin="30" end="29" isPushBackRoute="0" name="0"/>
    <arc begin="30" end="119" isPushBackRoute="0" name="0"/>
    <arc begin="119" end="30" isPushBackRoute="0" name="0"/>
    <arc begin="31" end="32" isPushBackRoute="0" name="0"/>
    <arc begin="32" end="31" isPushBackRoute="0" name="0"/>
    <arc begin="31" end="118" isPushBackRoute="0" name="0"/>
    <arc begin="118" end="31" isPushBackRoute="0" name="0"/>
    <arc begin="32" end="115" isPushBackRoute="0" name="0"/>
    <arc begin="115" end="32" isPushBackRoute="0" name="0"/>
    <arc begin="33" end="110" isPushBackRoute="0" name="0"/>
    <arc begin="110" end="33" isPushBackRoute="0" name="0"/>
    <arc begin="33" end="113" isPushBackRoute="0" name="0"/>
    <arc begin="113" end="33" isPushBackRoute="0" name="0"/>
    <arc begin="34" end="112" isPushBackRoute="0" name="0"/>
    <arc begin="112" end="34" isPushBackRoute="0" name="0"/>
    <arc begin="34" end="122" isPushBackRoute="0" name="0"/>
    <arc begin="122" end="34" isPushBackRoute="0" name="0"/>
    <arc begin="35" end="123" isPushBackRoute="0" name="0"/>
    <arc begin="123" end="35" isPushBackRoute="0" name="0"/>
    <arc begin="35" end="124" isPushBackRoute="0" name="0"/>
    <arc begin="124" end="35" isPushBackRoute="0" name="0"/>
    <arc begin="35" end="132" isPushBackRoute="0" name="0"/>
    <arc begin="132" end="35" isPushBackRoute="0" name="0"/>
    <arc begin="36" end="50" isPushBackRoute="0" name="0"/>
    <arc begin="50" end="36" isPushBackRoute="0" name="0"/>
    <arc begin="36" end="126" isPushBackRoute="0" name="0"/>
    <arc begin="126" end="36" isPushBackRoute="0" name="0"/>
    <arc begin="36" end="127" isPushBackRoute="0" name="0"/>
    <arc begin="127" end="36" isPushBackRoute="0" name="0"/>
    <arc begin="37" end="51" isPushBackRoute="0" name="0"/>
    <arc begin="51" end="37" isPushBackRoute="0" name="0"/>
    <arc begin="37" end="67" isPushBackRoute="0" name="0"/>
    <arc begin="67" end="37" isPushBackRoute="0" name="0"/>
    <arc begin="37" end="78" isPushBackRoute="0" name="0"/>
    <arc begin="78" end="37" isPushBackRoute="0" name="0"/>
    <arc begin="38" end="57" isPushBackRoute="0" name="0"/>
    <arc begin="57" end="38" isPushBackRoute="0" name="0"/>
    <arc begin="38" end="74" isPushBackRoute="0" name="0"/>
    <arc begin="74" end="38" isPushBackRoute="0" name="0"/>
    <arc begin="38" end="172" isPushBackRoute="0" name="0"/>
    <arc begin="172" end="38" isPushBackRoute="0" name="0"/>
    <arc begin="39" end="40" isPushBackRoute="0" name="0"/>
    <arc begin="40" end="39" isPushBackRoute="0" name="0"/>
    <arc begin="39" end="54" isPushBackRoute="0" name="0"/>
    <arc begin="54" end="39" isPushBackRoute="0" name="0"/>
    <arc begin="40" end="41" isPushBackRoute="0" name="0"/>
    <arc begin="41" end="40" isPushBackRoute="0" name="0"/>
    <arc begin="41" end="42" isPushBackRoute="0" name="0"/>
    <arc begin="42" end="41" isPushBackRoute="0" name="0"/>
    <arc begin="42" end="43" isPushBackRoute="0" name="0"/>
    <arc begin="43" end="42" isPushBackRoute="0" name="0"/>
    <arc begin="43" end="44" isPushBackRoute="0" name="0"/>
    <arc begin="44" end="43" isPushBackRoute="0" name="0"/>
    <arc begin="43" end="87" isPushBackRoute="0" name="0"/>
    <arc begin="87" end="43" isPushBackRoute="0" name="0"/>
    <arc begin="44" end="83" isPushBackRoute="0" name="0"/>
    <arc begin="83" end="44" isPushBackRoute="0" name="0"/>
    <arc begin="45" end="84" isPushBackRoute="0" name="0"/>
    <arc begin="84" end="45" isPushBackRoute="0" name="0"/>
    <arc begin="45" end="85" isPushBackRoute="0" name="0"/>
    <arc begin="85" end="45" isPushBackRoute="0" name="0"/>
    <arc begin="46" end="47" isPushBackRoute="0" name="0"/>
    <arc begin="47" end="46" isPushBackRoute="0" name="0"/>
    <arc begin="46" end="86" isPushBackRoute="0" name="0"/>
    <arc begin="86" end="46" isPushBackRoute="0" name="0"/>
    <arc begin="47" end="80" isPushBackRoute="0" name="0"/>
    <arc begin="80" end="47" isPushBackRoute="0" name="0"/>
    <arc begin="48" end="79" isPushBackRoute="0" name="0"/>
    <arc begin="79" end="48" isPushBackRoute="0" name="0"/>
    <arc begin="48" end="80" isPushBackRoute="0" name="0"/>
    <arc begin="80" end="48" isPushBackRoute="0" name="0"/>
    <arc begin="49" end="79" isPushBackRoute="0" name="0"/>
    <arc begin="79" end="49" isPushBackRoute="0" name="0"/>
    <arc begin="50" end="51" isPushBackRoute="0" name="0"/>
    <arc begin="51" end="50" isPushBackRoute="0" name="0"/>
    <arc begin="50" end="104" isPushBackRoute="0" name="Route"/>
    <arc begin="104" end="50" isPushBackRoute="0" name="Route"/>
    <arc begin="51" end="98" isPushBackRoute="0" name="0"/>
    <arc begin="98" end="51" isPushBackRoute="0" name="0"/>
    <arc begin="52" end="55" isPushBackRoute="0" name="0"/>
    <arc begin="55" end="52" isPushBackRoute="0" name="0"/>
    <arc begin="52" end="150" isPushBackRoute="0" name="0"/>
    <arc begin="150" end="52" isPushBackRoute="0" name="0"/>
    <arc begin="53" end="56" isPushBackRoute="0" name="0"/>
    <arc begin="56" end="53" isPushBackRoute="0" name="0"/>
    <arc begin="53" end="57" isPushBackRoute="0" name="0"/>
    <arc begin="57" end="53" isPushBackRoute="0" name="0"/>
    <arc begin="53" end="176" isPushBackRoute="0" name="0"/>
    <arc begin="176" end="53" isPushBackRoute="0" name="0"/>
    <arc begin="52" end="54" isPushBackRoute="0" name="0"/>
    <arc begin="54" end="52" isPushBackRoute="0" name="0"/>
    <arc begin="54" end="183" isPushBackRoute="0" name="0"/>
    <arc begin="183" end="54" isPushBackRoute="0" name="0"/>
    <arc begin="55" end="56" isPushBackRoute="0" name="0"/>
    <arc begin="56" end="55" isPushBackRoute="0" name="0"/>
    <arc begin="55" end="180" isPushBackRoute="0" name="0"/>
    <arc begin="180" end="55" isPushBackRoute="0" name="0"/>
    <arc begin="56" end="178" isPushBackRoute="0" name="0"/>
    <arc begin="178" end="56" isPushBackRoute="0" name="0"/>
    <arc begin="57" end="174" isPushBackRoute="0" name="0"/>
    <arc begin="174" end="57" isPushBackRoute="0" name="0"/>
    <arc begin="58" end="174" isPushBackRoute="1" name="0"/>
    <arc begin="174" end="58" isPushBackRoute="1" name="0"/>
    <arc begin="59" end="172" isPushBackRoute="1" name="0"/>
    <arc begin="172" end="59" isPushBackRoute="1" name="0"/>
    <arc begin="60" end="68" isPushBackRoute="0" name="0"/>
    <arc begin="68" end="60" isPushBackRoute="0" name="0"/>
    <arc begin="60" end="73" isPushBackRoute="0" name="0"/>
    <arc begin="73" end="60" isPushBackRoute="0" name="0"/>
    <arc begin="61" end="69" isPushBackRoute="0" name="0"/>
    <arc begin="69" end="61" isPushBackRoute="0" name="0"/>
    <arc begin="61" end="71" isPushBackRoute="0" name="0"/>
    <arc begin="71" end="61" isPushBackRoute="0" name="0"/>
    <arc begin="61" end="156" isPushBackRoute="0" name="0"/>
    <arc begin="156" end="61" isPushBackRoute="0" name="0"/>
    <arc begin="62" end="70" isPushBackRoute="0" name="0"/>
    <arc begin="70" end="62" isPushBackRoute="0" name="0"/>
    <arc begin="62" end="72" isPushBackRoute="0" name="0"/>
    <arc begin="72" end="62" isPushBackRoute="0" name="0"/>
    <arc begin="62" end="148" isPushBackRoute="0" name="0"/>
    <arc begin="148" end="62" isPushBackRoute="0" name="0"/>
    <arc begin="63" end="67" isPushBackRoute="0" name="0"/>
    <arc begin="67" end="63" isPushBackRoute="0" name="0"/>
    <arc begin="63" end="71" isPushBackRoute="0" name="0"/>
    <arc begin="71" end="63" isPushBackRoute="0" name="0"/>
    <arc begin="63" end="142" isPushBackRoute="0" name="0"/>
    <arc begin="142" end="63" isPushBackRoute="0" name="0"/>
    <arc begin="64" end="68" isPushBackRoute="0" name="0"/>
    <arc begin="68" end="64" isPushBackRoute="0" name="0"/>
    <arc begin="64" end="72" isPushBackRoute="0" name="0"/>
    <arc begin="72" end="64" isPushBackRoute="0" name="0"/>
    <arc begin="64" end="121" isPushBackRoute="0" name="0"/>
    <arc begin="121" end="64" isPushBackRoute="0" name="0"/>
    <arc begin="65" end="69" isPushBackRoute="0" name="0"/>
    <arc begin="69" end="65" isPushBackRoute="0" name="0"/>
    <arc begin="65" end="73" isPushBackRoute="0" name="0"/>
    <arc begin="73" end="65" isPushBackRoute="0" name="0"/>
    <arc begin="65" end="160" isPushBackRoute="0" name="0"/>
    <arc begin="160" end="65" isPushBackRoute="0" name="0"/>
    <arc begin="66" end="70" isPushBackRoute="0" name="0"/>
    <arc begin="70" end="66" isPushBackRoute="0" name="0"/>
    <arc begin="66" end="74" isPushBackRoute="0" name="0"/>
    <arc begin="74" end="66" isPushBackRoute="0" name="0"/>
    <arc begin="66" end="146" isPushBackRoute="0" name="0"/>
    <arc begin="146" end="66" isPushBackRoute="0" name="0"/>
    <arc begin="67" end="143" isPushBackRoute="0" name="0"/>
    <arc begin="143" end="67" isPushBackRoute="0" name="0"/>
    <arc begin="68" end="164" isPushBackRoute="0" name="0"/>
    <arc begin="164" end="68" isPushBackRoute="0" name="0"/>
    <arc begin="69" end="158" isPushBackRoute="0" name="0"/>
    <arc begin="158" end="69" isPushBackRoute="0" name="0"/>
    <arc begin="70" end="145" isPushBackRoute="0" name="0"/>
    <arc begin="145" end="70" isPushBackRoute="0" name="0"/>
    <arc begin="71" end="154" isPushBackRoute="0" name="0"/>
    <arc begin="154" end="71" isPushBackRoute="0" name="0"/>
    <arc begin="72" end="149" isPushBackRoute="0" name="0"/>
    <arc begin="149" end="72" isPushBackRoute="0" name="0"/>
    <arc begin="73" end="162" isPushBackRoute="0" name="0"/>
    <arc begin="162" end="73" isPushBackRoute="0" name="0"/>
    <arc begin="74" end="147" isPushBackRoute="0" name="0"/>
    <arc begin="147" end="74" isPushBackRoute="0" name="0"/>
    <arc begin="75" end="147" isPushBackRoute="1" name="0"/>
    <arc begin="147" end="75" isPushBackRoute="1" name="0"/>
    <arc begin="76" end="146" isPushBackRoute="1" name="0"/>
    <arc begin="146" end="76" isPushBackRoute="1" name="0"/>
    <arc begin="77" end="145" isPushBackRoute="1" name="0"/>
    <arc begin="145" end="77" isPushBackRoute="1" name="0"/>
    <arc begin="78" end="127" isPushBackRoute="0" name="0"/>
    <arc begin="127" end="78" isPushBackRoute="0" name="0"/>
    <arc begin="78" end="144" isPushBackRoute="0" name="0"/>
    <arc begin="144" end="78" isPushBackRoute="0" name="0"/>
    <arc begin="81" end="85" isPushBackRoute="0" name="0"/>
    <arc begin="85" end="81" isPushBackRoute="0" name="0"/>
    <arc begin="81" end="86" isPushBackRoute="0" name="0"/>
    <arc begin="86" end="81" isPushBackRoute="0" name="0"/>
    <arc begin="82" end="83" isPushBackRoute="0" name="0"/>
    <arc begin="83" end="82" isPushBackRoute="0" name="0"/>
    <arc begin="82" end="84" isPushBackRoute="0" name="0"/>
    <arc begin="84" end="82" isPushBackRoute="0" name="0"/>
    <arc begin="87" end="88" isPushBackRoute="0" name="Route"/>
    <arc begin="88" end="87" isPushBackRoute="0" name="Route"/>
    <arc begin="88" end="89" isPushBackRoute="0" name="Route"/>
    <arc begin="89" end="88" isPushBackRoute="0" name="Route"/>
    <arc begin="89" end="90" isPushBackRoute="0" name="Route"/>
    <arc begin="90" end="89" isPushBackRoute="0" name="Route"/>
    <arc begin="89" end="103" isPushBackRoute="0" name="Route"/>
    <arc begin="103" end="89" isPushBackRoute="0" name="Route"/>
    <arc begin="90" end="91" isPushBackRoute="0" name="Route"/>
    <arc begin="91" end="90" isPushBackRoute="0" name="Route"/>
    <arc begin="90" end="93" isPushBackRoute="0" name="Route"/>
    <arc begin="93" end="90" isPushBackRoute="0" name="Route"/>
    <arc begin="91" end="92" isPushBackRoute="0" name="Route"/>
    <arc begin="92" end="91" isPushBackRoute="0" name="Route"/>
    <arc begin="93" end="94" isPushBackRoute="0" name="Route"/>
    <arc begin="94" end="93" isPushBackRoute="0" name="Route"/>
    <arc begin="94" end="95" isPushBackRoute="0" name="Route"/>
    <arc begin="95" end="94" isPushBackRoute="0" name="Route"/>
    <arc begin="95" end="96" isPushBackRoute="0" name="Route"/>
    <arc begin="96" end="95" isPushBackRoute="0" name="Route"/>
    <arc begin="96" end="97" isPushBackRoute="0" name="Route"/>
    <arc begin="97" end="96" isPushBackRoute="0" name="Route"/>
    <arc begin="98" end="99" isPushBackRoute="0" name="Route"/>
    <arc begin="99" end="98" isPushBackRoute="0" name="Route"/>
    <arc begin="98" end="87" isPushBackRoute="0" name="0"/>
    <arc begin="87" end="98" isPushBackRoute="0" name="0"/>
    <arc begin="99" end="100" isPushBackRoute="0" name="Route"/>
    <arc begin="100" end="99" isPushBackRoute="0" name="Route"/>
    <arc begin="100" end="101" isPushBackRoute="0" name="Route"/>
    <arc begin="101" end="100" isPushBackRoute="0" name="Route"/>
    <arc begin="101" end="102" isPushBackRoute="0" name="Route"/>
    <arc begin="102" end="101" isPushBackRoute="0" name="Route"/>
    <arc begin="102" end="103" isPushBackRoute="0" name="Route"/>
    <arc begin="103" end="102" isPushBackRoute="0" name="Route"/>
    <arc begin="104" end="105" isPushBackRoute="0" name="Route"/>
    <arc begin="105" end="104" isPushBackRoute="0" name="Route"/>
    <arc begin="105" end="106" isPushBackRoute="0" name="Route"/>
    <arc begin="106" end="105" isPushBackRoute="0" name="Route"/>
    <arc begin="106" end="107" isPushBackRoute="0" name="Route"/>
    <arc begin="107" end="106" isPushBackRoute="0" name="Route"/>
    <arc begin="107" end="108" isPushBackRoute="0" name="Route"/>
    <arc begin="108" end="107" isPushBackRoute="0" name="Route"/>
    <arc begin="108" end="109" isPushBackRoute="0" name="Route"/>
    <arc begin="109" end="108" isPushBackRoute="0" name="Route"/>
    <arc begin="110" end="111" isPushBackRoute="0" name="0"/>
    <arc begin="111" end="110" isPushBackRoute="0" name="0"/>
    <arc begin="111" end="112" isPushBackRoute="0" name="0"/>
    <arc begin="112" end="111" isPushBackRoute="0" name="0"/>
    <arc begin="113" end="116" isPushBackRoute="0" name="0"/>
    <arc begin="116" end="113" isPushBackRoute="0" name="0"/>
    <arc begin="114" end="115" isPushBackRoute="0" name="0"/>
    <arc begin="115" end="114" isPushBackRoute="0" name="0"/>
    <arc begin="114" end="116" isPushBackRoute="0" name="0"/>
    <arc begin="116" end="114" isPushBackRoute="0" name="0"/>
    <arc begin="117" end="118" isPushBackRoute="0" name="0"/>
    <arc begin="118" end="117" isPushBackRoute="0" name="0"/>
    <arc begin="117" end="120" isPushBackRoute="0" name="0"/>
    <arc begin="120" end="117" isPushBackRoute="0" name="0"/>
    <arc begin="119" end="120" isPushBackRoute="0" name="0"/>
    <arc begin="120" end="119" isPushBackRoute="0" name="0"/>
    <arc begin="121" end="201" isPushBackRoute="1" name="Route"/>
    <arc begin="201" end="121" isPushBackRoute="1" name="Route"/>
    <arc begin="201" end="166" isPushBackRoute="1" name="Route"/>
    <arc begin="166" end="201" isPushBackRoute="1" name="Route"/>
    <arc begin="22" end="128" isPushBackRoute="1" name="0"/>
    <arc begin="128" end="22" isPushBackRoute="1" name="0"/>
    <arc begin="23" end="130" isPushBackRoute="1" name="0"/>
    <arc begin="130" end="23" isPushBackRoute="1" name="0"/>
    <arc begin="24" end="132" isPushBackRoute="1" name="0"/>
    <arc begin="132" end="24" isPushBackRoute="1" name="0"/>
    <arc begin="25" end="135" isPushBackRoute="1" name="0"/>
    <arc begin="135" end="25" isPushBackRoute="1" name="0"/>
    <arc begin="26" end="134" isPushBackRoute="1" name="0"/>
    <arc begin="134" end="26" isPushBackRoute="1" name="0"/>
    <arc begin="27" end="136" isPushBackRoute="1" name="0"/>
    <arc begin="136" end="27" isPushBackRoute="1" name="0"/>
    <arc begin="28" end="137" isPushBackRoute="1" name="0"/>
    <arc begin="137" end="28" isPushBackRoute="1" name="0"/>
    <arc begin="122" end="123" isPushBackRoute="0" name="0"/>
    <arc begin="123" end="122" isPushBackRoute="0" name="0"/>
    <arc begin="122" end="128" isPushBackRoute="0" name="0"/>
    <arc begin="128" end="122" isPushBackRoute="0" name="0"/>
    <arc begin="123" end="130" isPushBackRoute="0" name="Route"/>
    <arc begin="130" end="123" isPushBackRoute="0" name="Route"/>
    <arc begin="124" end="125" isPushBackRoute="0" name="0"/>
    <arc begin="125" end="124" isPushBackRoute="0" name="0"/>
    <arc begin="124" end="134" isPushBackRoute="0" name="0"/>
    <arc begin="134" end="124" isPushBackRoute="0" name="0"/>
    <arc begin="125" end="126" isPushBackRoute="0" name="0"/>
    <arc begin="126" end="125" isPushBackRoute="0" name="0"/>
    <arc begin="125" end="135" isPushBackRoute="0" name="0"/>
    <arc begin="135" end="125" isPushBackRoute="0" name="0"/>
    <arc begin="126" end="136" isPushBackRoute="0" name="0"/>
    <arc begin="136" end="126" isPushBackRoute="0" name="0"/>
    <arc begin="127" end="137" isPushBackRoute="0" name="Route"/>
    <arc begin="137" end="127" isPushBackRoute="0" name="Route"/>
    <arc begin="128" end="185" isPushBackRoute="1" name="0"/>
    <arc begin="185" end="128" isPushBackRoute="1" name="0"/>
    <arc begin="185" end="129" isPushBackRoute="1" name="0"/>
    <arc begin="129" end="185" isPushBackRoute="1" name="0"/>
    <arc begin="130" end="186" isPushBackRoute="1" name="0"/>
    <arc begin="186" end="130" isPushBackRoute="1" name="0"/>
    <arc begin="186" end="131" isPushBackRoute="1" name="0"/>
    <arc begin="131" end="186" isPushBackRoute="1" name="0"/>
    <arc begin="132" end="187" isPushBackRoute="1" name="Route"/>
    <arc begin="187" end="132" isPushBackRoute="1" name="Route"/>
    <arc begin="187" end="133" isPushBackRoute="1" name="Route"/>
    <arc begin="133" end="187" isPushBackRoute="1" name="Route"/>
    <arc begin="134" end="188" isPushBackRoute="1" name="Route"/>
    <arc begin="188" end="134" isPushBackRoute="1" name="Route"/>
    <arc begin="188" end="138" isPushBackRoute="1" name="Route"/>
    <arc begin="138" end="188" isPushBackRoute="1" name="Route"/>
    <arc begin="135" end="189" isPushBackRoute="1" name="Route"/>
    <arc begin="189" end="135" isPushBackRoute="1" name="Route"/>
    <arc begin="189" end="139" isPushBackRoute="1" name="Route"/>
    <arc begin="139" end="189" isPushBackRoute="1" name="Route"/>
    <arc begin="136" end="190" isPushBackRoute="1" name="0"/>
    <arc begin="190" end="136" isPushBackRoute="1" name="0"/>
    <arc begin="190" end="140" isPushBackRoute="1" name="0"/>
    <arc begin="140" end="190" isPushBackRoute="1" name="0"/>
    <arc begin="137" end="191" isPushBackRoute="1" name="Route"/>
    <arc begin="191" end="137" isPushBackRoute="1" name="Route"/>
    <arc begin="191" end="141" isPushBackRoute="1" name="Route"/>
    <arc begin="141" end="191" isPushBackRoute="1" name="Route"/>
    <arc begin="142" end="194" isPushBackRoute="1" name="Route"/>
    <arc begin="194" end="142" isPushBackRoute="1" name="Route"/>
    <arc begin="194" end="153" isPushBackRoute="1" name="Route"/>
    <arc begin="153" end="194" isPushBackRoute="1" name="Route"/>
    <arc begin="143" end="193" isPushBackRoute="1" name="Route"/>
    <arc begin="193" end="143" isPushBackRoute="1" name="Route"/>
    <arc begin="193" end="152" isPushBackRoute="1" name="Route"/>
    <arc begin="152" end="193" isPushBackRoute="1" name="Route"/>
    <arc begin="144" end="192" isPushBackRoute="1" name="Route"/>
    <arc begin="192" end="144" isPushBackRoute="1" name="Route"/>
    <arc begin="192" end="151" isPushBackRoute="1" name="Route"/>
    <arc begin="151" end="192" isPushBackRoute="1" name="Route"/>
    <arc begin="145" end="204" isPushBackRoute="1" name="Route"/>
    <arc begin="204" end="145" isPushBackRoute="1" name="Route"/>
    <arc begin="204" end="169" isPushBackRoute="1" name="Route"/>
    <arc begin="169" end="204" isPushBackRoute="1" name="Route"/>
    <arc begin="146" end="205" isPushBackRoute="1" name="Route"/>
    <arc begin="205" end="146" isPushBackRoute="1" name="Route"/>
    <arc begin="205" end="170" isPushBackRoute="1" name="Route"/>
    <arc begin="170" end="205" isPushBackRoute="1" name="Route"/>
    <arc begin="147" end="206" isPushBackRoute="1" name="Route"/>
    <arc begin="206" end="147" isPushBackRoute="1" name="Route"/>
    <arc begin="206" end="171" isPushBackRoute="1" name="Route"/>
    <arc begin="171" end="206" isPushBackRoute="1" name="Route"/>
    <arc begin="148" end="203" isPushBackRoute="1" name="Route"/>
    <arc begin="203" end="148" isPushBackRoute="1" name="Route"/>
    <arc begin="203" end="168" isPushBackRoute="1" name="Route"/>
    <arc begin="168" end="203" isPushBackRoute="1" name="Route"/>
    <arc begin="149" end="202" isPushBackRoute="1" name="Route"/>
    <arc begin="202" end="149" isPushBackRoute="1" name="Route"/>
    <arc begin="202" end="167" isPushBackRoute="1" name="Route"/>
    <arc begin="167" end="202" isPushBackRoute="1" name="Route"/>
    <arc begin="150" end="212" isPushBackRoute="1" name="Route"/>
    <arc begin="212" end="150" isPushBackRoute="1" name="Route"/>
    <arc begin="212" end="182" isPushBackRoute="1" name="Route"/>
    <arc begin="182" end="212" isPushBackRoute="1" name="Route"/>
    <arc begin="154" end="195" isPushBackRoute="1" name="Route"/>
    <arc begin="195" end="154" isPushBackRoute="1" name="Route"/>
    <arc begin="195" end="155" isPushBackRoute="1" name="Route"/>
    <arc begin="155" end="195" isPushBackRoute="1" name="Route"/>
    <arc begin="156" end="196" isPushBackRoute="1" name="Route"/>
    <arc begin="196" end="156" isPushBackRoute="1" name="Route"/>
    <arc begin="196" end="157" isPushBackRoute="1" name="Route"/>
    <arc begin="157" end="196" isPushBackRoute="1" name="Route"/>
    <arc begin="158" end="197" isPushBackRoute="1" name="Route"/>
    <arc begin="197" end="158" isPushBackRoute="1" name="Route"/>
    <arc begin="197" end="159" isPushBackRoute="1" name="Route"/>
    <arc begin="159" end="197" isPushBackRoute="1" name="Route"/>
    <arc begin="160" end="198" isPushBackRoute="1" name="Route"/>
    <arc begin="198" end="160" isPushBackRoute="1" name="Route"/>
    <arc begin="198" end="161" isPushBackRoute="1" name="Route"/>
    <arc begin="161" end="198" isPushBackRoute="1" name="Route"/>
    <arc begin="162" end="199" isPushBackRoute="1" name="Route"/>
    <arc begin="199" end="162" isPushBackRoute="1" name="Route"/>
    <arc begin="199" end="163" isPushBackRoute="1" name="Route"/>
    <arc begin="163" end="199" isPushBackRoute="1" name="Route"/>
    <arc begin="164" end="200" isPushBackRoute="1" name="Route"/>
    <arc begin="200" end="164" isPushBackRoute="1" name="Route"/>
    <arc begin="200" end="165" isPushBackRoute="1" name="Route"/>
    <arc begin="165" end="200" isPushBackRoute="1" name="Route"/>
    <arc begin="172" end="207" isPushBackRoute="1" name="Route"/>
    <arc begin="207" end="172" isPushBackRoute="1" name="Route"/>
    <arc begin="207" end="173" isPushBackRoute="1" name="Route"/>
    <arc begin="173" end="207" isPushBackRoute="1" name="Route"/>
    <arc begin="174" end="208" isPushBackRoute="1" name="Route"/>
    <arc begin="208" end="174" isPushBackRoute="1" name="Route"/>
    <arc begin="208" end="175" isPushBackRoute="1" name="Route"/>
    <arc begin="175" end="208" isPushBackRoute="1" name="Route"/>
    <arc begin="176" end="209" isPushBackRoute="1" name="Route"/>
    <arc begin="209" end="176" isPushBackRoute="1" name="Route"/>
    <arc begin="209" end="177" isPushBackRoute="1" name="Route"/>
    <arc begin="177" end="209" isPushBackRoute="1" name="Route"/>
    <arc begin="178" end="210" isPushBackRoute="1" name="Route"/>
    <arc begin="210" end="178" isPushBackRoute="1" name="Route"/>
    <arc begin="210" end="179" isPushBackRoute="1" name="Route"/>
    <arc begin="179" end="210" isPushBackRoute="1" name="Route"/>
    <arc begin="180" end="211" isPushBackRoute="1" name="Route"/>
    <arc begin="211" end="180" isPushBackRoute="1" name="Route"/>
    <arc begin="211" end="181" isPushBackRoute="1" name="Route"/>
    <arc begin="181" end="211" isPushBackRoute="1" name="Route"/>
    <arc begin="183" end="213" isPushBackRoute="1" name="Route"/>
    <arc begin="213" end="183" isPushBackRoute="1" name="Route"/>
    <arc begin="213" end="184" isPushBackRoute="1" name="Route"/>
    <arc begin="184" end="213" isPushBackRoute="1" name="Route"/>
  </TaxiWaySegments>
</groundnet>