<?xml version="1.0"?>
<groundnet>
  <version>1</version>
  <fgaversion>Wed, 23 Jun 2021 14:56:53 GMT by FlightgearAirports 0.0.33</fgaversion>
  <name>gooneybird</name>
  <frequencies>
    <APPROACH>12427</APPROACH>
    <APPROACH>12210</APPROACH>
    <APPROACH>12607</APPROACH>
    <GROUND>12160</GROUND>
    <TOWER>12210</TOWER>
    <TOWER>11910</TOWER>
  </frequencies>
  <parkingList>
    <Parking index="0" type="gate" lat="N43 41.859" lon="E10 23.916" heading="9.0" radius="18" name="LIRP-" number="24" pushBackRoute="141"/>
    <Parking index="1" type="gate" lat="N43 41.8572" lon="E10 23.9478" heading="9.0" radius="18" name="LIRP-" number="25" pushBackRoute="143"/>
    <Parking index="2" type="gate" lat="N43 41.8542" lon="E10 23.9838" heading="9.0" radius="18" name="LIRP-" number="26" pushBackRoute="137"/>
    <Parking index="3" type="gate" lat="N43 41.859" lon="E10 24.0912" heading="9.0" radius="18" name="LIRP-" number="29" pushBackRoute="135"/>
    <Parking index="4" type="gate" lat="N43 41.8488" lon="E10 24.0192" heading="9.0" radius="18" name="LIRP-" number="27" pushBackRoute="131"/>
    <Parking index="5" type="gate" lat="N43 41.8542" lon="E10 24.0552" heading="9.0" radius="18" name="LIRP-" number="28" pushBackRoute="133"/>
    <Parking index="6" type="gate" lat="N43 41.8548" lon="E10 23.8548" heading="325.0" radius="33" name="LIRP-" number="21" pushBackRoute="139"/>
    <Parking index="7" type="gate" lat="N43 41.6868" lon="E10 23.8032" heading="325.0" radius="18" name="LIRP-" number="11"/>
    <Parking index="8" type="cargo" lat="N43 41.721" lon="E10 23.8122" heading="325.0" radius="26" name="LIRP-" number="13"/>
    <Parking index="9" type="cargo" lat="N43 41.763" lon="E10 23.8212" heading="325.0" radius="33" name="LIRP-" number="15"/>
    <Parking index="10" type="gate" lat="N43 41.799" lon="E10 23.829" heading="325.0" radius="18" name="LIRP-" number="17"/>
    <Parking index="11" type="gate" lat="N43 41.7822" lon="E10 23.931" heading="52.0" radius="18" name="LIRP-" number="54"/>
    <Parking index="12" type="gate" lat="N43 41.7102" lon="E10 23.913" heading="99.0" radius="14" name="LIRP-" number="50"/>
    <Parking index="13" type="gate" lat="N43 41.7342" lon="E10 23.919" heading="99.0" radius="14" name="LIRP-" number="51"/>
    <Parking index="14" type="gate" lat="N43 41.7552" lon="E10 23.9232" heading="99.0" radius="14" name="LIRP-" number="53"/>
    <Parking index="15" type="gate" lat="N43 41.709" lon="E10 23.9808" heading="148.0" radius="14" name="LIRP-" number="41"/>
    <Parking index="16" type="gate" lat="N43 41.7318" lon="E10 23.9922" heading="122.0" radius="18" name="LIRP-" number="42"/>
    <Parking index="17" type="gate" lat="N43 41.7567" lon="E10 23.99562" heading="122.0" radius="18" name="LIRP-" number="43"/>
    <Parking index="18" type="gate" lat="N43 41.781" lon="E10 23.9958" heading="52.0" radius="14" name="LIRP-" number="44"/>
    <Parking index="19" type="ga" lat="N43 41.9268" lon="E10 24.2058" heading="78.0" radius="10" name="LIRP-ga-" number="38" pushBackRoute="178"/>
    <Parking index="20" type="ga" lat="N43 41.9118" lon="E10 24.1938" heading="78.0" radius="10" name="LIRP-ga-" number="34"/>
    <Parking index="21" type="ga" lat="N43 41.8992" lon="E10 24.1842" heading="78.0" radius="7.5" name="LIRP-ga-" number="31"/>
    <Parking index="22" type="ga" lat="N43 41.889" lon="E10 24.1818" heading="78.0" radius="7.5" name="LIRP-ga-" number="30" pushBackRoute="176"/>
    <Parking index="23" type="ga" lat="N43 41.9112" lon="E10 24.1482" heading="258.0" radius="10" name="LIRP-ga-" number="33"/>
    <Parking index="24" type="ga" lat="N43 41.9238" lon="E10 24.1578" heading="258.0" radius="10" name="LIRP-ga-" number="385" pushBackRoute="164"/>
    <Parking index="25" type="ga" lat="N43 41.9352" lon="E10 24.168" heading="258.0" radius="10" name="LIRP-ga-" number="39" pushBackRoute="151"/>
  </parkingList>
  <TaxiNodes>
    <node index="26" lat="N43 41.5338" lon="E10 24.1812" isOnRunway="1" holdPointType="none"/>
    <node index="27" lat="N43 41.5698" lon="E10 24.1728" isOnRunway="0" holdPointType="none"/>
    <node index="28" lat="N43 41.589" lon="E10 24.138" isOnRunway="0" holdPointType="normal"/>
    <node index="29" lat="N43 41.6148" lon="E10 24.0912" isOnRunway="0" holdPointType="none"/>
    <node index="30" lat="N43 41.6358" lon="E10 24.0618" isOnRunway="0" holdPointType="none"/>
    <node index="31" lat="N43 41.6028" lon="E10 24.0552" isOnRunway="1" holdPointType="none"/>
    <node index="32" lat="N43 41.697" lon="E10 24.0498" isOnRunway="0" holdPointType="normal"/>
    <node index="33" lat="N43 41.8062" lon="E10 24.0288" isOnRunway="0" holdPointType="none"/>
    <node index="34" lat="N43 41.8368" lon="E10 24.1158" isOnRunway="0" holdPointType="none"/>
    <node index="35" lat="N43 41.8458" lon="E10 24.1242" isOnRunway="0" holdPointType="none"/>
    <node index="36" lat="N43 41.841" lon="E10 24.1212" isOnRunway="0" holdPointType="none"/>
    <node index="37" lat="N43 41.8878" lon="E10 24.138" isOnRunway="0" holdPointType="none"/>
    <node index="38" lat="N43 41.8098" lon="E10 24.0102" isOnRunway="0" holdPointType="none"/>
    <node index="39" lat="N43 41.81412" lon="E10 23.9703" isOnRunway="0" holdPointType="none"/>
    <node index="40" lat="N43 41.82084" lon="E10 23.90682" isOnRunway="0" holdPointType="none"/>
    <node index="41" lat="N43 41.8062" lon="E10 23.8818" isOnRunway="0" holdPointType="none"/>
    <node index="42" lat="N43 41.7048" lon="E10 23.8608" isOnRunway="0" holdPointType="none"/>
    <node index="43" lat="N43 41.6922" lon="E10 23.865" isOnRunway="0" holdPointType="none"/>
    <node index="44" lat="N43 41.682" lon="E10 23.8878" isOnRunway="0" holdPointType="none"/>
    <node index="45" lat="N43 41.6862" lon="E10 23.874" isOnRunway="0" holdPointType="none"/>
    <node index="46" lat="N43 41.6982" lon="E10 23.8608" isOnRunway="0" holdPointType="none"/>
    <node index="47" lat="N43 41.6802" lon="E10 23.9082" isOnRunway="0" holdPointType="none"/>
    <node index="48" lat="N43 41.664" lon="E10 23.9292" isOnRunway="0" holdPointType="none"/>
    <node index="49" lat="N43 41.592" lon="E10 23.9412" isOnRunway="0" holdPointType="normal"/>
    <node index="50" lat="N43 41.676" lon="E10 23.919" isOnRunway="0" holdPointType="none"/>
    <node index="51" lat="N43 41.6712" lon="E10 23.9262" isOnRunway="0" holdPointType="none"/>
    <node index="52" lat="N43 41.5062" lon="E10 23.9532" isOnRunway="1" holdPointType="none"/>
    <node index="53" lat="N43 40.9398" lon="E10 23.3688" isOnRunway="1" holdPointType="none"/>
    <node index="54" lat="N43 40.5918" lon="E10 23.0088" isOnRunway="1" holdPointType="none"/>
    <node index="55" lat="N43 40.59132" lon="E10 22.97244" isOnRunway="0" holdPointType="none"/>
    <node index="56" lat="N43 40.6023" lon="E10 22.95264" isOnRunway="0" holdPointType="normal"/>
    <node index="57" lat="N43 40.7196" lon="E10 22.89678" isOnRunway="0" holdPointType="none"/>
    <node index="58" lat="N43 41.01672" lon="E10 23.20452" isOnRunway="0" holdPointType="none"/>
    <node index="59" lat="N43 41.0166" lon="E10 23.22834" isOnRunway="0" holdPointType="none"/>
    <node index="60" lat="N43 40.9638" lon="E10 23.3238" isOnRunway="0" holdPointType="normal"/>
    <node index="61" lat="N43 40.6224" lon="E10 22.91562" isOnRunway="0" holdPointType="none"/>
    <node index="62" lat="N43 40.64706" lon="E10 22.87992" isOnRunway="0" holdPointType="none"/>
    <node index="63" lat="N43 41.0187" lon="E10 23.22186" isOnRunway="0" holdPointType="none"/>
    <node index="64" lat="N43 40.5678" lon="E10 23.013" isOnRunway="0" holdPointType="none"/>
    <node index="65" lat="N43 40.5432" lon="E10 23.0592" isOnRunway="0" holdPointType="normal"/>
    <node index="66" lat="N43 40.5228" lon="E10 23.0958" isOnRunway="0" holdPointType="none"/>
    <node index="67" lat="N43 40.5168" lon="E10 23.136" isOnRunway="1" holdPointType="none"/>
    <node index="68" lat="N43 41.826" lon="E10 24.0828" isOnRunway="0" holdPointType="none"/>
    <node index="69" lat="N43 41.811" lon="E10 24.0438" isOnRunway="0" holdPointType="none"/>
    <node index="70" lat="N43 41.8008" lon="E10 23.9682" isOnRunway="0" holdPointType="none"/>
    <node index="71" lat="N43 41.6538" lon="E10 23.9352" isOnRunway="0" holdPointType="none"/>
    <node index="72" lat="N43 41.637" lon="E10 23.934" isOnRunway="0" holdPointType="none"/>
    <node index="73" lat="N43 41.81358" lon="E10 23.97408" isOnRunway="0" holdPointType="none"/>
    <node index="74" lat="N43 41.8176" lon="E10 23.93748" isOnRunway="0" holdPointType="none"/>
    <node index="75" lat="N43 41.8158" lon="E10 23.8908" isOnRunway="0" holdPointType="none"/>
    <node index="76" lat="N43 41.745" lon="E10 23.86914" isOnRunway="0" holdPointType="none"/>
    <node index="77" lat="N43 41.73" lon="E10 23.8662" isOnRunway="0" holdPointType="none"/>
    <node index="78" lat="N43 41.7882" lon="E10 23.8782" isOnRunway="0" holdPointType="none"/>
    <node index="79" lat="N43 41.7402" lon="E10 23.868" isOnRunway="0" holdPointType="none"/>
    <node index="80" lat="N43 41.772" lon="E10 23.8752" isOnRunway="0" holdPointType="none"/>
    <node index="81" lat="N43 41.8128" lon="E10 23.8278" isOnRunway="0" holdPointType="none"/>
    <node index="82" lat="N43 41.793" lon="E10 23.8338" isOnRunway="0" holdPointType="none"/>
    <node index="83" lat="N43 41.8062" lon="E10 23.8218" isOnRunway="0" holdPointType="none"/>
    <node index="84" lat="N43 41.7483" lon="E10 23.83554" isOnRunway="0" holdPointType="none"/>
    <node index="85" lat="N43 41.778" lon="E10 23.8212" isOnRunway="0" holdPointType="none"/>
    <node index="86" lat="N43 41.772" lon="E10 23.814" isOnRunway="0" holdPointType="none"/>
    <node index="87" lat="N43 41.7378" lon="E10 23.8128" isOnRunway="0" holdPointType="none"/>
    <node index="88" lat="N43 41.7069" lon="E10 23.8254" isOnRunway="0" holdPointType="none"/>
    <node index="89" lat="N43 41.7318" lon="E10 23.802" isOnRunway="0" holdPointType="none"/>
    <node index="90" lat="N43 41.6748" lon="E10 23.8638" isOnRunway="0" holdPointType="none"/>
    <node index="91" lat="N43 41.6988" lon="E10 23.811" isOnRunway="0" holdPointType="none"/>
    <node index="92" lat="N43 41.67132" lon="E10 23.81862" isOnRunway="0" holdPointType="none"/>
    <node index="93" lat="N43 41.6922" lon="E10 23.7972" isOnRunway="0" holdPointType="none"/>
    <node index="94" lat="N43 41.811" lon="E10 23.8218" isOnRunway="0" holdPointType="none"/>
    <node index="95" lat="N43 41.7762" lon="E10 23.8152" isOnRunway="0" holdPointType="none"/>
    <node index="96" lat="N43 41.7372" lon="E10 23.805" isOnRunway="0" holdPointType="none"/>
    <node index="97" lat="N43 41.6982" lon="E10 23.8002" isOnRunway="0" holdPointType="none"/>
    <node index="98" lat="N43 41.7312" lon="E10 23.952" isOnRunway="0" holdPointType="none"/>
    <node index="99" lat="N43 41.7768" lon="E10 23.9628" isOnRunway="0" holdPointType="none"/>
    <node index="100" lat="N43 41.70006" lon="E10 23.9451" isOnRunway="0" holdPointType="none"/>
    <node index="101" lat="N43 41.7858" lon="E10 23.9652" isOnRunway="0" holdPointType="none"/>
    <node index="102" lat="N43 41.70636" lon="E10 23.94642" isOnRunway="0" holdPointType="none"/>
    <node index="103" lat="N43 41.7522" lon="E10 23.9568" isOnRunway="0" holdPointType="none"/>
    <node index="104" lat="N43 41.6718" lon="E10 23.9388" isOnRunway="0" holdPointType="none"/>
    <node index="105" lat="N43 41.77974" lon="E10 23.87658" isOnRunway="0" holdPointType="none"/>
    <node index="106" lat="N43 41.77428" lon="E10 23.91648" isOnRunway="0" holdPointType="none"/>
    <node index="107" lat="N43 41.7888" lon="E10 23.9442" isOnRunway="0" holdPointType="none"/>
    <node index="108" lat="N43 41.7612" lon="E10 23.8728" isOnRunway="0" holdPointType="none"/>
    <node index="109" lat="N43 41.7162" lon="E10 23.8638" isOnRunway="0" holdPointType="none"/>
    <node index="110" lat="N43 41.7492" lon="E10 24.0402" isOnRunway="0" holdPointType="none"/>
    <node index="111" lat="N43 41.7342" lon="E10 24.0432" isOnRunway="0" holdPointType="none"/>
    <node index="112" lat="N43 41.7918" lon="E10 24.0318" isOnRunway="0" holdPointType="none"/>
    <node index="113" lat="N43 41.79" lon="E10 24.012" isOnRunway="0" holdPointType="none"/>
    <node index="114" lat="N43 41.775" lon="E10 23.9832" isOnRunway="0" holdPointType="none"/>
    <node index="115" lat="N43 41.766" lon="E10 23.9598" isOnRunway="0" holdPointType="none"/>
    <node index="116" lat="N43 41.76336" lon="E10 23.98086" isOnRunway="0" holdPointType="none"/>
    <node index="117" lat="N43 41.7468" lon="E10 24.0192" isOnRunway="0" holdPointType="none"/>
    <node index="118" lat="N43 41.7432" lon="E10 23.955" isOnRunway="0" holdPointType="none"/>
    <node index="119" lat="N43 41.7402" lon="E10 23.973" isOnRunway="0" holdPointType="none"/>
    <node index="120" lat="N43 41.724" lon="E10 24.0102" isOnRunway="0" holdPointType="none"/>
    <node index="121" lat="N43 41.733" lon="E10 24.027" isOnRunway="0" holdPointType="none"/>
    <node index="122" lat="N43 41.718" lon="E10 23.949" isOnRunway="0" holdPointType="none"/>
    <node index="123" lat="N43 41.7012" lon="E10 23.988" isOnRunway="0" holdPointType="none"/>
    <node index="124" lat="N43 41.7168" lon="E10 23.9742" isOnRunway="0" holdPointType="none"/>
    <node index="125" lat="N43 41.697" lon="E10 23.9808" isOnRunway="0" holdPointType="none"/>
    <node index="126" lat="N43 41.8272" lon="E10 23.9778" isOnRunway="0" holdPointType="none"/>
    <node index="127" lat="N43 41.8242" lon="E10 24.0132" isOnRunway="0" holdPointType="none"/>
    <node index="128" lat="N43 41.826" lon="E10 24.048" isOnRunway="0" holdPointType="none"/>
    <node index="129" lat="N43 41.8422" lon="E10 24.087" isOnRunway="0" holdPointType="none"/>
    <node index="130" lat="N43 41.8272" lon="E10 23.9868" isOnRunway="0" holdPointType="none"/>
    <node index="131" lat="N43 41.8272" lon="E10 23.9868" isOnRunway="0" holdPointType="PushBack"/>
    <node index="132" lat="N43 41.8242" lon="E10 24.069" isOnRunway="0" holdPointType="none"/>
    <node index="133" lat="N43 41.8242" lon="E10 24.069" isOnRunway="0" holdPointType="PushBack"/>
    <node index="134" lat="N43 41.841" lon="E10 24.1158" isOnRunway="0" holdPointType="none"/>
    <node index="135" lat="N43 41.841" lon="E10 24.1158" isOnRunway="0" holdPointType="PushBack"/>
    <node index="136" lat="N43 41.832" lon="E10 23.9472" isOnRunway="0" holdPointType="none"/>
    <node index="137" lat="N43 41.832" lon="E10 23.9472" isOnRunway="0" holdPointType="PushBack"/>
    <node index="138" lat="N43 41.8062" lon="E10 23.901" isOnRunway="0" holdPointType="none"/>
    <node index="139" lat="N43 41.8062" lon="E10 23.901" isOnRunway="0" holdPointType="PushBack"/>
    <node index="140" lat="N43 41.8092" lon="E10 23.9082" isOnRunway="0" holdPointType="none"/>
    <node index="141" lat="N43 41.8092" lon="E10 23.9082" isOnRunway="0" holdPointType="PushBack"/>
    <node index="142" lat="N43 41.8068" lon="E10 23.9352" isOnRunway="0" holdPointType="none"/>
    <node index="143" lat="N43 41.8068" lon="E10 23.9352" isOnRunway="0" holdPointType="PushBack"/>
    <node index="144" lat="N43 41.3328" lon="E10 23.775" isOnRunway="1" holdPointType="none"/>
    <node index="145" lat="N43 41.3088" lon="E10 23.7798" isOnRunway="0" holdPointType="none"/>
    <node index="146" lat="N43 41.286" lon="E10 23.8242" isOnRunway="0" holdPointType="normal"/>
    <node index="147" lat="N43 41.2638" lon="E10 23.8638" isOnRunway="0" holdPointType="none"/>
    <node index="148" lat="N43 41.2362" lon="E10 23.8722" isOnRunway="1" holdPointType="none"/>
    <node index="149" lat="N43 41.9088" lon="E10 24.171" isOnRunway="0" holdPointType="none"/>
    <node index="150" lat="N43 41.937" lon="E10 24.1998" isOnRunway="0" holdPointType="none"/>
    <node index="151" lat="N43 41.937" lon="E10 24.1998" isOnRunway="0" holdPointType="PushBack"/>
    <node index="152" lat="N43 41.898" lon="E10 24.1542" isOnRunway="0" holdPointType="none"/>
    <node index="153" lat="N43 41.8932" lon="E10 24.1458" isOnRunway="0" holdPointType="none"/>
    <node index="154" lat="N43 41.907" lon="E10 24.168" isOnRunway="0" holdPointType="none"/>
    <node index="155" lat="N43 41.928" lon="E10 24.1878" isOnRunway="0" holdPointType="none"/>
    <node index="156" lat="N43 41.916" lon="E10 24.177" isOnRunway="0" holdPointType="none"/>
    <node index="157" lat="N43 41.934" lon="E10 24.1932" isOnRunway="0" holdPointType="none"/>
    <node index="158" lat="N43 41.925" lon="E10 24.1962" isOnRunway="0" holdPointType="none"/>
    <node index="159" lat="N43 41.937" lon="E10 24.1842" isOnRunway="0" holdPointType="none"/>
    <node index="160" lat="N43 41.922" lon="E10 24.1818" isOnRunway="0" holdPointType="none"/>
    <node index="161" lat="N43 41.9118" lon="E10 24.1728" isOnRunway="0" holdPointType="none"/>
    <node index="162" lat="N43 41.9262" lon="E10 24.174" isOnRunway="0" holdPointType="none"/>
    <node index="163" lat="N43 41.9262" lon="E10 24.1872" isOnRunway="0" holdPointType="none"/>
    <node index="164" lat="N43 41.9262" lon="E10 24.1872" isOnRunway="0" holdPointType="PushBack"/>
    <node index="165" lat="N43 41.9112" lon="E10 24.1842" isOnRunway="0" holdPointType="none"/>
    <node index="166" lat="N43 41.9148" lon="E10 24.201" isOnRunway="0" holdPointType="none"/>
    <node index="167" lat="N43 41.913" lon="E10 24.1998" isOnRunway="0" holdPointType="none"/>
    <node index="168" lat="N43 41.9202" lon="E10 24.1908" isOnRunway="0" holdPointType="none"/>
    <node index="169" lat="N43 41.913" lon="E10 24.1638" isOnRunway="0" holdPointType="none"/>
    <node index="170" lat="N43 41.9088" lon="E10 24.1398" isOnRunway="0" holdPointType="none"/>
    <node index="171" lat="N43 41.8998" lon="E10 24.1902" isOnRunway="0" holdPointType="none"/>
    <node index="172" lat="N43 41.898" lon="E10 24.174" isOnRunway="0" holdPointType="none"/>
    <node index="173" lat="N43 41.9028" lon="E10 24.1902" isOnRunway="0" holdPointType="none"/>
    <node index="174" lat="N43 41.8872" lon="E10 24.1668" isOnRunway="0" holdPointType="none"/>
    <node index="175" lat="N43 41.8812" lon="E10 24.1662" isOnRunway="0" holdPointType="none"/>
    <node index="176" lat="N43 41.8812" lon="E10 24.1662" isOnRunway="0" holdPointType="PushBack"/>
    <node index="177" lat="N43 41.9328" lon="E10 24.1878" isOnRunway="0" holdPointType="none"/>
    <node index="178" lat="N43 41.9328" lon="E10 24.1878" isOnRunway="0" holdPointType="PushBack"/>
    <node index="179" lat="N43 41.268" lon="E10 23.9022" isOnRunway="1" holdPointType="none"/>
    <node index="180" lat="N43 41.6862" lon="E10 23.9418" isOnRunway="0" holdPointType="none"/>
    <node index="181" lat="N43 41.01906" lon="E10 23.21286" isOnRunway="0"/>
    <node index="182" lat="N43 40.67082" lon="E10 22.87266" isOnRunway="0"/>
    <node index="183" lat="N43 40.6968" lon="E10 22.88346" isOnRunway="0"/>
    <node index="184" lat="N43 40.68246" lon="E10 22.87572" isOnRunway="0"/>
    <node index="185" lat="N43 40.65768" lon="E10 22.87428" isOnRunway="0"/>
    <node index="186" lat="N43 40.635" lon="E10 22.89372" isOnRunway="0"/>
    <node index="187" lat="N43 41.81934" lon="E10 23.89794" isOnRunway="0"/>
  </TaxiNodes>
  <TaxiWaySegments>
    <arc begin="0" end="40" isPushBackRoute="1" name="0"/>
    <arc begin="40" end="0" isPushBackRoute="1" name="0"/>
    <arc begin="1" end="74" isPushBackRoute="1" name="0"/>
    <arc begin="74" end="1" isPushBackRoute="1" name="0"/>
    <arc begin="2" end="126" isPushBackRoute="1" name="0"/>
    <arc begin="126" end="2" isPushBackRoute="1" name="0"/>
    <arc begin="3" end="129" isPushBackRoute="1" name="0"/>
    <arc begin="129" end="3" isPushBackRoute="1" name="0"/>
    <arc begin="4" end="127" isPushBackRoute="1" name="0"/>
    <arc begin="127" end="4" isPushBackRoute="1" name="0"/>
    <arc begin="5" end="128" isPushBackRoute="1" name="0"/>
    <arc begin="128" end="5" isPushBackRoute="1" name="0"/>
    <arc begin="6" end="75" isPushBackRoute="1" name="0"/>
    <arc begin="75" end="6" isPushBackRoute="1" name="0"/>
    <arc begin="7" end="93" isPushBackRoute="0" name="0"/>
    <arc begin="8" end="89" isPushBackRoute="0" name="0"/>
    <arc begin="9" end="86" isPushBackRoute="0" name="0"/>
    <arc begin="10" end="83" isPushBackRoute="0" name="0"/>
    <arc begin="11" end="107" isPushBackRoute="0" name="0"/>
    <arc begin="12" end="102" isPushBackRoute="0" name="0"/>
    <arc begin="13" end="98" isPushBackRoute="0" name="0"/>
    <arc begin="14" end="103" isPushBackRoute="0" name="0"/>
    <arc begin="15" end="123" isPushBackRoute="0" name="0"/>
    <arc begin="16" end="120" isPushBackRoute="0" name="0"/>
    <arc begin="17" end="117" isPushBackRoute="0" name="0"/>
    <arc begin="18" end="113" isPushBackRoute="0" name="0"/>
    <arc begin="19" end="158" isPushBackRoute="1" name="0"/>
    <arc begin="158" end="19" isPushBackRoute="1" name="0"/>
    <arc begin="20" end="167" isPushBackRoute="0" name="0"/>
    <arc begin="21" end="171" isPushBackRoute="0" name="0"/>
    <arc begin="22" end="174" isPushBackRoute="1" name="0"/>
    <arc begin="174" end="22" isPushBackRoute="1" name="0"/>
    <arc begin="23" end="170" isPushBackRoute="0" name="0"/>
    <arc begin="24" end="162" isPushBackRoute="1" name="0"/>
    <arc begin="162" end="24" isPushBackRoute="1" name="0"/>
    <arc begin="25" end="159" isPushBackRoute="1" name="0"/>
    <arc begin="159" end="25" isPushBackRoute="1" name="0"/>
    <arc begin="26" end="27" isPushBackRoute="0" name="0"/>
    <arc begin="27" end="26" isPushBackRoute="0" name="0"/>
    <arc begin="27" end="28" isPushBackRoute="0" name="0"/>
    <arc begin="28" end="27" isPushBackRoute="0" name="0"/>
    <arc begin="28" end="29" isPushBackRoute="0" name="0"/>
    <arc begin="29" end="28" isPushBackRoute="0" name="0"/>
    <arc begin="29" end="30" isPushBackRoute="0" name="0"/>
    <arc begin="30" end="29" isPushBackRoute="0" name="0"/>
    <arc begin="30" end="31" isPushBackRoute="0" name="0"/>
    <arc begin="31" end="30" isPushBackRoute="0" name="0"/>
    <arc begin="30" end="32" isPushBackRoute="0" name="0"/>
    <arc begin="32" end="30" isPushBackRoute="0" name="0"/>
    <arc begin="31" end="52" isPushBackRoute="0" name="0"/>
    <arc begin="52" end="31" isPushBackRoute="0" name="0"/>
    <arc begin="32" end="111" isPushBackRoute="0" name="0"/>
    <arc begin="111" end="32" isPushBackRoute="0" name="0"/>
    <arc begin="33" end="38" isPushBackRoute="0" name="0"/>
    <arc begin="38" end="33" isPushBackRoute="0" name="0"/>
    <arc begin="33" end="69" isPushBackRoute="0" name="0"/>
    <arc begin="69" end="33" isPushBackRoute="0" name="0"/>
    <arc begin="33" end="112" isPushBackRoute="0" name="0"/>
    <arc begin="112" end="33" isPushBackRoute="0" name="0"/>
    <arc begin="34" end="36" isPushBackRoute="0" name="0"/>
    <arc begin="36" end="34" isPushBackRoute="0" name="0"/>
    <arc begin="34" end="68" isPushBackRoute="0" name="0"/>
    <arc begin="68" end="34" isPushBackRoute="0" name="0"/>
    <arc begin="35" end="36" isPushBackRoute="0" name="0"/>
    <arc begin="36" end="35" isPushBackRoute="0" name="0"/>
    <arc begin="35" end="37" isPushBackRoute="0" name="0"/>
    <arc begin="37" end="35" isPushBackRoute="0" name="0"/>
    <arc begin="37" end="153" isPushBackRoute="0" name="0"/>
    <arc begin="153" end="37" isPushBackRoute="0" name="0"/>
    <arc begin="38" end="73" isPushBackRoute="0" name="0"/>
    <arc begin="73" end="38" isPushBackRoute="0" name="0"/>
    <arc begin="38" end="127" isPushBackRoute="0" name="0"/>
    <arc begin="127" end="38" isPushBackRoute="0" name="0"/>
    <arc begin="39" end="70" isPushBackRoute="0" name="0"/>
    <arc begin="70" end="39" isPushBackRoute="0" name="0"/>
    <arc begin="39" end="73" isPushBackRoute="0" name="0"/>
    <arc begin="73" end="39" isPushBackRoute="0" name="0"/>
    <arc begin="39" end="74" isPushBackRoute="0" name="0"/>
    <arc begin="74" end="39" isPushBackRoute="0" name="0"/>
    <arc begin="40" end="74" isPushBackRoute="0" name="0"/>
    <arc begin="74" end="40" isPushBackRoute="0" name="0"/>
    <arc begin="40" end="187" isPushBackRoute="0" name="0"/>
    <arc begin="187" end="40" isPushBackRoute="0" name="0"/>
    <arc begin="40" end="140" isPushBackRoute="1" name="0"/>
    <arc begin="140" end="40" isPushBackRoute="1" name="0"/>
    <arc begin="41" end="75" isPushBackRoute="0" name="0"/>
    <arc begin="75" end="41" isPushBackRoute="0" name="0"/>
    <arc begin="41" end="78" isPushBackRoute="0" name="0"/>
    <arc begin="78" end="41" isPushBackRoute="0" name="0"/>
    <arc begin="42" end="46" isPushBackRoute="0" name="0"/>
    <arc begin="46" end="42" isPushBackRoute="0" name="0"/>
    <arc begin="42" end="88" isPushBackRoute="0" name="0"/>
    <arc begin="42" end="109" isPushBackRoute="0" name="0"/>
    <arc begin="109" end="42" isPushBackRoute="0" name="0"/>
    <arc begin="43" end="45" isPushBackRoute="0" name="0"/>
    <arc begin="45" end="43" isPushBackRoute="0" name="0"/>
    <arc begin="43" end="46" isPushBackRoute="0" name="0"/>
    <arc begin="46" end="43" isPushBackRoute="0" name="0"/>
    <arc begin="44" end="45" isPushBackRoute="0" name="0"/>
    <arc begin="45" end="44" isPushBackRoute="0" name="0"/>
    <arc begin="44" end="47" isPushBackRoute="0" name="0"/>
    <arc begin="47" end="44" isPushBackRoute="0" name="0"/>
    <arc begin="45" end="90" isPushBackRoute="0" name="0"/>
    <arc begin="47" end="50" isPushBackRoute="0" name="0"/>
    <arc begin="50" end="47" isPushBackRoute="0" name="0"/>
    <arc begin="48" end="51" isPushBackRoute="0" name="0"/>
    <arc begin="51" end="48" isPushBackRoute="0" name="0"/>
    <arc begin="48" end="72" isPushBackRoute="0" name="0"/>
    <arc begin="72" end="48" isPushBackRoute="0" name="0"/>
    <arc begin="52" end="49" isPushBackRoute="0" name="0"/>
    <arc begin="49" end="72" isPushBackRoute="0" name="0"/>
    <arc begin="50" end="51" isPushBackRoute="0" name="0"/>
    <arc begin="51" end="50" isPushBackRoute="0" name="0"/>
    <arc begin="52" end="144" isPushBackRoute="0" name="0"/>
    <arc begin="144" end="52" isPushBackRoute="0" name="0"/>
    <arc begin="53" end="60" isPushBackRoute="0" name="0"/>
    <arc begin="60" end="53" isPushBackRoute="0" name="0"/>
    <arc begin="53" end="144" isPushBackRoute="0" name="0"/>
    <arc begin="144" end="53" isPushBackRoute="0" name="0"/>
    <arc begin="54" end="55" isPushBackRoute="0" name="0"/>
    <arc begin="55" end="54" isPushBackRoute="0" name="0"/>
    <arc begin="55" end="56" isPushBackRoute="0" name="0"/>
    <arc begin="56" end="55" isPushBackRoute="0" name="0"/>
    <arc begin="55" end="64" isPushBackRoute="0" name="0"/>
    <arc begin="64" end="55" isPushBackRoute="0" name="0"/>
    <arc begin="56" end="61" isPushBackRoute="0" name="0"/>
    <arc begin="61" end="56" isPushBackRoute="0" name="0"/>
    <arc begin="57" end="58" isPushBackRoute="0" name="0"/>
    <arc begin="58" end="57" isPushBackRoute="0" name="0"/>
    <arc begin="57" end="183" isPushBackRoute="0" name="0"/>
    <arc begin="183" end="57" isPushBackRoute="0" name="0"/>
    <arc begin="58" end="181" isPushBackRoute="0" name="0"/>
    <arc begin="181" end="58" isPushBackRoute="0" name="0"/>
    <arc begin="59" end="60" isPushBackRoute="0" name="0"/>
    <arc begin="60" end="59" isPushBackRoute="0" name="0"/>
    <arc begin="59" end="63" isPushBackRoute="0" name="0"/>
    <arc begin="63" end="59" isPushBackRoute="0" name="0"/>
    <arc begin="61" end="186" isPushBackRoute="0" name="0"/>
    <arc begin="186" end="61" isPushBackRoute="0" name="0"/>
    <arc begin="64" end="65" isPushBackRoute="0" name="0"/>
    <arc begin="65" end="64" isPushBackRoute="0" name="0"/>
    <arc begin="65" end="66" isPushBackRoute="0" name="0"/>
    <arc begin="66" end="65" isPushBackRoute="0" name="0"/>
    <arc begin="66" end="67" isPushBackRoute="0" name="0"/>
    <arc begin="67" end="66" isPushBackRoute="0" name="0"/>
    <arc begin="68" end="69" isPushBackRoute="0" name="0"/>
    <arc begin="69" end="68" isPushBackRoute="0" name="0"/>
    <arc begin="68" end="129" isPushBackRoute="0" name="0"/>
    <arc begin="129" end="68" isPushBackRoute="0" name="0"/>
    <arc begin="69" end="128" isPushBackRoute="0" name="0"/>
    <arc begin="128" end="69" isPushBackRoute="0" name="0"/>
    <arc begin="70" end="101" isPushBackRoute="0" name="0"/>
    <arc begin="101" end="70" isPushBackRoute="0" name="0"/>
    <arc begin="71" end="72" isPushBackRoute="0" name="0"/>
    <arc begin="72" end="71" isPushBackRoute="0" name="0"/>
    <arc begin="71" end="104" isPushBackRoute="0" name="0"/>
    <arc begin="104" end="71" isPushBackRoute="0" name="0"/>
    <arc begin="73" end="126" isPushBackRoute="0" name="0"/>
    <arc begin="126" end="73" isPushBackRoute="0" name="0"/>
    <arc begin="74" end="142" isPushBackRoute="1" name="0"/>
    <arc begin="142" end="74" isPushBackRoute="1" name="0"/>
    <arc begin="75" end="138" isPushBackRoute="1" name="0"/>
    <arc begin="138" end="75" isPushBackRoute="1" name="0"/>
    <arc begin="76" end="79" isPushBackRoute="0" name="0"/>
    <arc begin="79" end="76" isPushBackRoute="0" name="0"/>
    <arc begin="76" end="84" isPushBackRoute="0" name="0"/>
    <arc begin="76" end="108" isPushBackRoute="0" name="0"/>
    <arc begin="108" end="76" isPushBackRoute="0" name="0"/>
    <arc begin="77" end="79" isPushBackRoute="0" name="0"/>
    <arc begin="79" end="77" isPushBackRoute="0" name="0"/>
    <arc begin="77" end="109" isPushBackRoute="0" name="0"/>
    <arc begin="109" end="77" isPushBackRoute="0" name="0"/>
    <arc begin="78" end="82" isPushBackRoute="0" name="0"/>
    <arc begin="78" end="105" isPushBackRoute="0" name="0"/>
    <arc begin="105" end="78" isPushBackRoute="0" name="0"/>
    <arc begin="79" end="13" isPushBackRoute="0" name="0"/>
    <arc begin="80" end="105" isPushBackRoute="0" name="0"/>
    <arc begin="105" end="80" isPushBackRoute="0" name="0"/>
    <arc begin="80" end="108" isPushBackRoute="0" name="0"/>
    <arc begin="108" end="80" isPushBackRoute="0" name="0"/>
    <arc begin="81" end="41" isPushBackRoute="0" name="0"/>
    <arc begin="82" end="10" isPushBackRoute="0" name="0"/>
    <arc begin="83" end="94" isPushBackRoute="0" name="0"/>
    <arc begin="84" end="9" isPushBackRoute="0" name="0"/>
    <arc begin="85" end="80" isPushBackRoute="0" name="0"/>
    <arc begin="86" end="95" isPushBackRoute="0" name="0"/>
    <arc begin="87" end="77" isPushBackRoute="0" name="0"/>
    <arc begin="88" end="8" isPushBackRoute="0" name="0"/>
    <arc begin="89" end="96" isPushBackRoute="0" name="0"/>
    <arc begin="90" end="92" isPushBackRoute="0" name="0"/>
    <arc begin="91" end="46" isPushBackRoute="0" name="0"/>
    <arc begin="92" end="7" isPushBackRoute="0" name="0"/>
    <arc begin="93" end="97" isPushBackRoute="0" name="0"/>
    <arc begin="94" end="81" isPushBackRoute="0" name="0"/>
    <arc begin="95" end="85" isPushBackRoute="0" name="0"/>
    <arc begin="96" end="87" isPushBackRoute="0" name="0"/>
    <arc begin="97" end="91" isPushBackRoute="0" name="0"/>
    <arc begin="98" end="118" isPushBackRoute="0" name="0"/>
    <arc begin="118" end="98" isPushBackRoute="0" name="0"/>
    <arc begin="98" end="122" isPushBackRoute="0" name="0"/>
    <arc begin="122" end="98" isPushBackRoute="0" name="0"/>
    <arc begin="99" end="101" isPushBackRoute="0" name="0"/>
    <arc begin="101" end="99" isPushBackRoute="0" name="0"/>
    <arc begin="99" end="114" isPushBackRoute="0" name="0"/>
    <arc begin="99" end="115" isPushBackRoute="0" name="0"/>
    <arc begin="115" end="99" isPushBackRoute="0" name="0"/>
    <arc begin="100" end="102" isPushBackRoute="0" name="0"/>
    <arc begin="102" end="100" isPushBackRoute="0" name="0"/>
    <arc begin="100" end="180" isPushBackRoute="0" name="0"/>
    <arc begin="180" end="100" isPushBackRoute="0" name="0"/>
    <arc begin="102" end="122" isPushBackRoute="0" name="0"/>
    <arc begin="122" end="102" isPushBackRoute="0" name="0"/>
    <arc begin="103" end="115" isPushBackRoute="0" name="0"/>
    <arc begin="115" end="103" isPushBackRoute="0" name="0"/>
    <arc begin="103" end="118" isPushBackRoute="0" name="0"/>
    <arc begin="118" end="103" isPushBackRoute="0" name="0"/>
    <arc begin="105" end="106" isPushBackRoute="0" name="0"/>
    <arc begin="106" end="11" isPushBackRoute="0" name="0"/>
    <arc begin="107" end="101" isPushBackRoute="0" name="0"/>
    <arc begin="108" end="14" isPushBackRoute="0" name="0"/>
    <arc begin="109" end="12" isPushBackRoute="0" name="0"/>
    <arc begin="110" end="111" isPushBackRoute="0" name="0"/>
    <arc begin="111" end="110" isPushBackRoute="0" name="0"/>
    <arc begin="110" end="112" isPushBackRoute="0" name="0"/>
    <arc begin="112" end="110" isPushBackRoute="0" name="0"/>
    <arc begin="113" end="112" isPushBackRoute="0" name="0"/>
    <arc begin="114" end="18" isPushBackRoute="0" name="0"/>
    <arc begin="115" end="116" isPushBackRoute="0" name="0"/>
    <arc begin="116" end="17" isPushBackRoute="0" name="0"/>
    <arc begin="117" end="110" isPushBackRoute="0" name="0"/>
    <arc begin="118" end="119" isPushBackRoute="0" name="0"/>
    <arc begin="119" end="16" isPushBackRoute="0" name="0"/>
    <arc begin="120" end="121" isPushBackRoute="0" name="0"/>
    <arc begin="121" end="111" isPushBackRoute="0" name="0"/>
    <arc begin="122" end="124" isPushBackRoute="0" name="0"/>
    <arc begin="123" end="125" isPushBackRoute="0" name="0"/>
    <arc begin="124" end="15" isPushBackRoute="0" name="0"/>
    <arc begin="125" end="100" isPushBackRoute="0" name="0"/>
    <arc begin="126" end="136" isPushBackRoute="1" name="0"/>
    <arc begin="136" end="126" isPushBackRoute="1" name="0"/>
    <arc begin="127" end="130" isPushBackRoute="1" name="0"/>
    <arc begin="130" end="127" isPushBackRoute="1" name="0"/>
    <arc begin="128" end="132" isPushBackRoute="1" name="0"/>
    <arc begin="132" end="128" isPushBackRoute="1" name="0"/>
    <arc begin="129" end="134" isPushBackRoute="1" name="0"/>
    <arc begin="134" end="129" isPushBackRoute="1" name="0"/>
    <arc begin="130" end="131" isPushBackRoute="1" name="0"/>
    <arc begin="131" end="130" isPushBackRoute="1" name="0"/>
    <arc begin="132" end="133" isPushBackRoute="1" name="0"/>
    <arc begin="133" end="132" isPushBackRoute="1" name="0"/>
    <arc begin="134" end="135" isPushBackRoute="1" name="0"/>
    <arc begin="135" end="134" isPushBackRoute="1" name="0"/>
    <arc begin="136" end="137" isPushBackRoute="1" name="0"/>
    <arc begin="137" end="136" isPushBackRoute="1" name="0"/>
    <arc begin="138" end="139" isPushBackRoute="1" name="0"/>
    <arc begin="139" end="138" isPushBackRoute="1" name="0"/>
    <arc begin="140" end="141" isPushBackRoute="1" name="0"/>
    <arc begin="141" end="140" isPushBackRoute="1" name="0"/>
    <arc begin="142" end="143" isPushBackRoute="1" name="0"/>
    <arc begin="143" end="142" isPushBackRoute="1" name="0"/>
    <arc begin="144" end="145" isPushBackRoute="0" name="0"/>
    <arc begin="145" end="144" isPushBackRoute="0" name="0"/>
    <arc begin="145" end="146" isPushBackRoute="0" name="0"/>
    <arc begin="146" end="145" isPushBackRoute="0" name="0"/>
    <arc begin="146" end="147" isPushBackRoute="0" name="0"/>
    <arc begin="147" end="146" isPushBackRoute="0" name="0"/>
    <arc begin="147" end="148" isPushBackRoute="0" name="0"/>
    <arc begin="148" end="147" isPushBackRoute="0" name="0"/>
    <arc begin="149" end="154" isPushBackRoute="0" name="0"/>
    <arc begin="154" end="149" isPushBackRoute="0" name="0"/>
    <arc begin="149" end="161" isPushBackRoute="0" name="0"/>
    <arc begin="161" end="149" isPushBackRoute="0" name="0"/>
    <arc begin="149" end="169" isPushBackRoute="0" name="0"/>
    <arc begin="150" end="151" isPushBackRoute="1" name="0"/>
    <arc begin="151" end="150" isPushBackRoute="1" name="0"/>
    <arc begin="150" end="157" isPushBackRoute="1" name="0"/>
    <arc begin="157" end="150" isPushBackRoute="1" name="0"/>
    <arc begin="152" end="153" isPushBackRoute="0" name="0"/>
    <arc begin="153" end="152" isPushBackRoute="0" name="0"/>
    <arc begin="152" end="154" isPushBackRoute="0" name="0"/>
    <arc begin="154" end="152" isPushBackRoute="0" name="0"/>
    <arc begin="152" end="172" isPushBackRoute="0" name="0"/>
    <arc begin="153" end="174" isPushBackRoute="0" name="0"/>
    <arc begin="174" end="153" isPushBackRoute="0" name="0"/>
    <arc begin="155" end="157" isPushBackRoute="0" name="0"/>
    <arc begin="157" end="155" isPushBackRoute="0" name="0"/>
    <arc begin="155" end="158" isPushBackRoute="1" name="0"/>
    <arc begin="158" end="155" isPushBackRoute="1" name="0"/>
    <arc begin="155" end="160" isPushBackRoute="0" name="0"/>
    <arc begin="160" end="155" isPushBackRoute="0" name="0"/>
    <arc begin="156" end="160" isPushBackRoute="0" name="0"/>
    <arc begin="160" end="156" isPushBackRoute="0" name="0"/>
    <arc begin="156" end="161" isPushBackRoute="0" name="0"/>
    <arc begin="161" end="156" isPushBackRoute="0" name="0"/>
    <arc begin="157" end="159" isPushBackRoute="1" name="0"/>
    <arc begin="159" end="157" isPushBackRoute="1" name="0"/>
    <arc begin="160" end="162" isPushBackRoute="1" name="0"/>
    <arc begin="162" end="160" isPushBackRoute="1" name="0"/>
    <arc begin="160" end="163" isPushBackRoute="1" name="0"/>
    <arc begin="163" end="160" isPushBackRoute="1" name="0"/>
    <arc begin="161" end="165" isPushBackRoute="0" name="0"/>
    <arc begin="163" end="164" isPushBackRoute="1" name="0"/>
    <arc begin="164" end="163" isPushBackRoute="1" name="0"/>
    <arc begin="165" end="20" isPushBackRoute="0" name="0"/>
    <arc begin="166" end="168" isPushBackRoute="0" name="0"/>
    <arc begin="167" end="166" isPushBackRoute="0" name="0"/>
    <arc begin="168" end="160" isPushBackRoute="0" name="0"/>
    <arc begin="169" end="23" isPushBackRoute="0" name="0"/>
    <arc begin="170" end="153" isPushBackRoute="0" name="0"/>
    <arc begin="171" end="173" isPushBackRoute="0" name="0"/>
    <arc begin="172" end="21" isPushBackRoute="0" name="0"/>
    <arc begin="173" end="154" isPushBackRoute="0" name="0"/>
    <arc begin="174" end="175" isPushBackRoute="1" name="0"/>
    <arc begin="175" end="174" isPushBackRoute="1" name="0"/>
    <arc begin="175" end="176" isPushBackRoute="1" name="0"/>
    <arc begin="176" end="175" isPushBackRoute="1" name="0"/>
    <arc begin="155" end="177" isPushBackRoute="1" name="0"/>
    <arc begin="177" end="155" isPushBackRoute="1" name="0"/>
    <arc begin="177" end="178" isPushBackRoute="1" name="0"/>
    <arc begin="178" end="177" isPushBackRoute="1" name="0"/>
    <arc begin="147" end="179" isPushBackRoute="0" name="0"/>
    <arc begin="179" end="147" isPushBackRoute="0" name="0"/>
    <arc begin="180" end="104" isPushBackRoute="0" name="0"/>
    <arc begin="104" end="180" isPushBackRoute="0" name="0"/>
    <arc begin="47" end="180" isPushBackRoute="0" name="0"/>
    <arc begin="180" end="47" isPushBackRoute="0" name="0"/>
    <arc begin="181" end="63" isPushBackRoute="0" name="0"/>
    <arc begin="63" end="181" isPushBackRoute="0" name="0"/>
    <arc begin="182" end="185" isPushBackRoute="0" name="0"/>
    <arc begin="185" end="182" isPushBackRoute="0" name="0"/>
    <arc begin="183" end="184" isPushBackRoute="0" name="0"/>
    <arc begin="184" end="183" isPushBackRoute="0" name="0"/>
    <arc begin="184" end="182" isPushBackRoute="0" name="0"/>
    <arc begin="182" end="184" isPushBackRoute="0" name="0"/>
    <arc begin="185" end="62" isPushBackRoute="0" name="0"/>
    <arc begin="62" end="185" isPushBackRoute="0" name="0"/>
    <arc begin="186" end="62" isPushBackRoute="0" name="0"/>
    <arc begin="62" end="186" isPushBackRoute="0" name="0"/>
    <arc begin="187" end="75" isPushBackRoute="0" name="0"/>
    <arc begin="75" end="187" isPushBackRoute="0" name="0"/>
  </TaxiWaySegments>
</groundnet>